[{"Actor": {"id": "4764f6bd-bc2b-4a60-b095-114fed6158e2", "label": "Mohamed Kenawi"}, "AddedToDatabase": "2023-05-03", "Country": {"id": "c08b6e33-a244-415b-8bb1-b1f0949fc581", "label": "Algeria"}, "Date": "2022-03-07", "Grid": {"id": "9e276df3-a6ef-46c8-884d-8b54f28223fc", "label": "E01N35-24"}, "ID": "509f190b-bdea-4954-97eb-e49c33477d44", "Role": {"id": "20b1a4e0-97e1-41f7-b519-124a7317266b", "label": "EAMENA Project Staff"}, "Label": "EAMENA-0196973", "Tiles": [["Resource Summary", 1], ["Archaeological Assessment ", 1], ["Geometry", 1], ["Geography", 1], ["Assessment Summary", 1], ["Modern Country Territory", 1], ["Geometry Location Observation", 1], ["Assessment Activity", 1]]}, {"Actor": {"id": "4764f6bd-bc2b-4a60-b095-114fed6158e2", "label": "Mohamed Kenawi"}, "AddedToDatabase": "2023-05-03", "Country": {"id": "c08b6e33-a244-415b-8bb1-b1f0949fc581", "label": "Algeria"}, "Date": "2022-03-07", "Grid": {"id": "9e276df3-a6ef-46c8-884d-8b54f28223fc", "label": "E01N35-24"}, "ID": "96736580-148b-40bc-bed0-85594fba2a8a", "Role": {"id": "20b1a4e0-97e1-41f7-b519-124a7317266b", "label": "EAMENA Project Staff"}, "Label": "EAMENA-0196975", "Tiles": [["Modern Country Territory", 1], ["Assessment Summary", 1], ["Assessment Activity", 1], ["Geography", 1], ["Geometry", 1], ["Resource Summary", 1], ["Geometry Location Observation", 1]]}, {"Actor": {"id": "4764f6bd-bc2b-4a60-b095-114fed6158e2", "label": "Mohamed Kenawi"}, "AddedToDatabase": "2023-05-03", "Country": {"id": "c08b6e33-a244-415b-8bb1-b1f0949fc581", "label": "Algeria"}, "Date": "2022-03-07", "Grid": {"id": "9e276df3-a6ef-46c8-884d-8b54f28223fc", "label": "E01N35-24"}, "ID": "9ace9598-1d34-41bf-9f97-44e783e396af", "Role": {"id": "20b1a4e0-97e1-41f7-b519-124a7317266b", "label": "EAMENA Project Staff"}, "Label": "EAMENA-0196971", "Tiles": [["Geometry", 1], ["Geography", 1], ["Assessment Activity", 1], ["Assessment Summary", 1], ["Geometry Location Observation", 1], ["Modern Country Territory", 1], ["Archaeological Assessment ", 1], ["Resource Summary", 1]]}, {"Actor": {"id": "4764f6bd-bc2b-4a60-b095-114fed6158e2", "label": "Mohamed Kenawi"}, "AddedToDatabase": "2023-05-03", "Country": {"id": "c08b6e33-a244-415b-8bb1-b1f0949fc581", "label": "Algeria"}, "Date": "2022-03-07", "Grid": {"id": "9e276df3-a6ef-46c8-884d-8b54f28223fc", "label": "E01N35-24"}, "ID": "9d16beda-5ead-4175-a9fd-54322d6e138d", "Role": {"id": "20b1a4e0-97e1-41f7-b519-124a7317266b", "label": "EAMENA Project Staff"}, "Label": "EAMENA-0196978", "Tiles": [["Geography", 1], ["Assessment Activity", 1], ["Geometry", 1], ["Geometry Location Observation", 1], ["Resource Summary", 1], ["Modern Country Territory", 1], ["Assessment Summary", 1]]}, {"Actor": {"id": "4764f6bd-bc2b-4a60-b095-114fed6158e2", "label": "Mohamed Kenawi"}, "AddedToDatabase": "2023-05-03", "Country": {"id": "c08b6e33-a244-415b-8bb1-b1f0949fc581", "label": "Algeria"}, "Date": "2022-03-07", "Grid": {"id": "9e276df3-a6ef-46c8-884d-8b54f28223fc", "label": "E01N35-24"}, "ID": "9f5913de-71df-40f2-b0e0-33b2930b1230", "Role": {"id": "20b1a4e0-97e1-41f7-b519-124a7317266b", "label": "EAMENA Project Staff"}, "Label": "EAMENA-0196974", "Tiles": [["Resource Summary", 1], ["Assessment Activity", 1], ["Geography", 1], ["Assessment Summary", 1], ["Geometry", 1], ["Geometry Location Observation", 1], ["Modern Country Territory", 1]]}, {"Actor": {"id": "4764f6bd-bc2b-4a60-b095-114fed6158e2", "label": "Mohamed Kenawi"}, "AddedToDatabase": "2023-05-03", "Country": {"id": "c08b6e33-a244-415b-8bb1-b1f0949fc581", "label": "Algeria"}, "Date": "2022-03-07", "Grid": {"id": "9e276df3-a6ef-46c8-884d-8b54f28223fc", "label": "E01N35-24"}, "ID": "a33c53eb-d704-42d3-b141-b1db9539e8f8", "Role": {"id": "20b1a4e0-97e1-41f7-b519-124a7317266b", "label": "EAMENA Project Staff"}, "Label": "EAMENA-0196976", "Tiles": [["Modern Country Territory", 1], ["Resource Summary", 1], ["Assessment Activity", 1], ["Geometry", 1], ["Assessment Summary", 1], ["Geometry Location Observation", 1], ["Geography", 1]]}, {"Actor": {"id": "4764f6bd-bc2b-4a60-b095-114fed6158e2", "label": "Mohamed Kenawi"}, "AddedToDatabase": "2023-05-03", "Country": {"id": "c08b6e33-a244-415b-8bb1-b1f0949fc581", "label": "Algeria"}, "Date": "2022-03-07", "Grid": {"id": "9e276df3-a6ef-46c8-884d-8b54f28223fc", "label": "E01N35-24"}, "ID": "cc0274f2-1f26-4d55-b677-9a2c49f9c9a4", "Role": {"id": "20b1a4e0-97e1-41f7-b519-124a7317266b", "label": "EAMENA Project Staff"}, "Label": "EAMENA-0196977", "Tiles": [["Assessment Summary", 1], ["Modern Country Territory", 1], ["Geometry", 1], ["Geography", 1], ["Assessment Activity", 1], ["Resource Summary", 1], ["Geometry Location Observation", 1]]}, {"Actor": {"id": "4764f6bd-bc2b-4a60-b095-114fed6158e2", "label": "Mohamed Kenawi"}, "AddedToDatabase": "2023-05-03", "Country": {"id": "c08b6e33-a244-415b-8bb1-b1f0949fc581", "label": "Algeria"}, "Date": "2022-03-07", "Grid": {"id": "9e276df3-a6ef-46c8-884d-8b54f28223fc", "label": "E01N35-24"}, "ID": "eb811225-d0a0-422d-a33d-e7655102b553", "Role": {"id": "20b1a4e0-97e1-41f7-b519-124a7317266b", "label": "EAMENA Project Staff"}, "Label": "EAMENA-0196972", "Tiles": [["Geometry", 1], ["Assessment Activity", 1], ["Geometry Location Observation", 1], ["Geography", 1], ["Archaeological Assessment ", 1], ["Modern Country Territory", 1], ["Assessment Summary", 1], ["Resource Summary", 1]]}]