{"sites": [{"Actor": {"id": "90ae76cf-865d-4e68-971c-c2b2af9be18c", "label": "Michael Fradley"}, "AddedToDatabase": "2026-05-11", "Country": {"id": "15db88c0-04a2-4c80-9973-076572711d7a", "label": "Saudi Arabia"}, "Date": "2026-04-24", "Grid": {"id": "ff291798-aaa7-4f8b-b072-1c8819ac454c", "label": "E36N27-12"}, "ID": "023982fb-74b5-46d8-84b6-24a79c291282", "MissingFields": [], "Role": {"id": "20b1a4e0-97e1-41f7-b519-124a7317266b", "label": "EAMENA Project Staff"}, "Label": "EAMENA-0284960", "Disturbances": [], "Tiles": [["Archaeological Assessment", 1], ["Assessment Summary", 2], ["Condition Assessment", 2], ["Environment Assessment", 1], ["Geography", 2], ["Geometries", 2], ["Resource Summary", 1]]}, {"Actor": {"id": "90ae76cf-865d-4e68-971c-c2b2af9be18c", "label": "Michael Fradley"}, "AddedToDatabase": "2026-05-11", "Country": {"id": "15db88c0-04a2-4c80-9973-076572711d7a", "label": "Saudi Arabia"}, "Date": "2026-04-24", "Grid": {"id": "ff291798-aaa7-4f8b-b072-1c8819ac454c", "label": "E36N27-12"}, "ID": "19860fd7-08d9-4e78-8906-286806734632", "MissingFields": [], "Role": {"id": "20b1a4e0-97e1-41f7-b519-124a7317266b", "label": "EAMENA Project Staff"}, "Label": "EAMENA-0284948", "Disturbances": [], "Tiles": [["Archaeological Assessment", 1], ["Assessment Summary", 2], ["Condition Assessment", 2], ["Environment Assessment", 1], ["Geography", 2], ["Geometries", 2], ["Resource Summary", 1]]}, {"Actor": {"id": "90ae76cf-865d-4e68-971c-c2b2af9be18c", "label": "Michael Fradley"}, "AddedToDatabase": "2026-05-11", "Country": {"id": "15db88c0-04a2-4c80-9973-076572711d7a", "label": "Saudi Arabia"}, "Date": "2026-04-24", "Grid": {"id": "ff291798-aaa7-4f8b-b072-1c8819ac454c", "label": "E36N27-12"}, "ID": "1fc16c46-b046-4cd6-8051-25521900f689", "MissingFields": [], "Role": {"id": "20b1a4e0-97e1-41f7-b519-124a7317266b", "label": "EAMENA Project Staff"}, "Label": "EAMENA-0284944", "Disturbances": [], "Tiles": [["Archaeological Assessment", 1], ["Assessment Summary", 2], ["Condition Assessment", 2], ["Environment Assessment", 1], ["Geography", 2], ["Geometries", 2], ["Resource Summary", 1]]}, {"Actor": {"id": "90ae76cf-865d-4e68-971c-c2b2af9be18c", "label": "Michael Fradley"}, "AddedToDatabase": "2026-05-11", "Country": {"id": "15db88c0-04a2-4c80-9973-076572711d7a", "label": "Saudi Arabia"}, "Date": "2026-04-24", "Grid": {"id": "ff291798-aaa7-4f8b-b072-1c8819ac454c", "label": "E36N27-12"}, "ID": "20cda1f4-e127-4062-bb60-977af7f7ea75", "MissingFields": [], "Role": {"id": "20b1a4e0-97e1-41f7-b519-124a7317266b", "label": "EAMENA Project Staff"}, "Label": "EAMENA-0284945", "Disturbances": [], "Tiles": [["Archaeological Assessment", 1], ["Assessment Summary", 2], ["Condition Assessment", 2], ["Environment Assessment", 1], ["Geography", 2], ["Geometries", 2], ["Resource Summary", 1]]}, {"Actor": {"id": "90ae76cf-865d-4e68-971c-c2b2af9be18c", "label": "Michael Fradley"}, "AddedToDatabase": "2026-05-11", "Country": {"id": "15db88c0-04a2-4c80-9973-076572711d7a", "label": "Saudi Arabia"}, "Date": "2026-04-24", "Grid": {"id": "ff291798-aaa7-4f8b-b072-1c8819ac454c", "label": "E36N27-12"}, "ID": "2d035729-ff92-4a89-9e93-4a8a6a313371", "MissingFields": [], "Role": {"id": "20b1a4e0-97e1-41f7-b519-124a7317266b", "label": "EAMENA Project Staff"}, "Label": "EAMENA-0284935", "Disturbances": [], "Tiles": [["Archaeological Assessment", 1], ["Assessment Summary", 2], ["Condition Assessment", 2], ["Environment Assessment", 1], ["Geography", 2], ["Geometries", 2], ["Resource Summary", 1]]}, {"Actor": {"id": "90ae76cf-865d-4e68-971c-c2b2af9be18c", "label": "Michael Fradley"}, "AddedToDatabase": "2026-05-11", "Country": {"id": "15db88c0-04a2-4c80-9973-076572711d7a", "label": "Saudi Arabia"}, "Date": "2026-04-24", "Grid": {"id": "ff291798-aaa7-4f8b-b072-1c8819ac454c", "label": "E36N27-12"}, "ID": "30bbaeb9-7fb2-4543-b0bd-464a7042bb4d", "MissingFields": [], "Role": {"id": "20b1a4e0-97e1-41f7-b519-124a7317266b", "label": "EAMENA Project Staff"}, "Label": "EAMENA-0284953", "Disturbances": [], "Tiles": [["Archaeological Assessment", 1], ["Assessment Summary", 2], ["Condition Assessment", 2], ["Environment Assessment", 1], ["Geography", 2], ["Geometries", 2], ["Resource Summary", 1]]}, {"Actor": {"id": "90ae76cf-865d-4e68-971c-c2b2af9be18c", "label": "Michael Fradley"}, "AddedToDatabase": "2026-05-11", "Country": {"id": "15db88c0-04a2-4c80-9973-076572711d7a", "label": "Saudi Arabia"}, "Date": "2026-04-24", "Grid": {"id": "ff291798-aaa7-4f8b-b072-1c8819ac454c", "label": "E36N27-12"}, "ID": "31ea706d-2e67-4200-af21-a6a5ab105ad5", "MissingFields": [], "Role": {"id": "20b1a4e0-97e1-41f7-b519-124a7317266b", "label": "EAMENA Project Staff"}, "Label": "EAMENA-0284958", "Disturbances": [], "Tiles": [["Archaeological Assessment", 1], ["Assessment Summary", 2], ["Condition Assessment", 2], ["Environment Assessment", 1], ["Geography", 2], ["Geometries", 2], ["Resource Summary", 1]]}, {"Actor": {"id": "90ae76cf-865d-4e68-971c-c2b2af9be18c", "label": "Michael Fradley"}, "AddedToDatabase": "2026-05-11", "Country": {"id": "15db88c0-04a2-4c80-9973-076572711d7a", "label": "Saudi Arabia"}, "Date": "2026-04-24", "Grid": {"id": "ff291798-aaa7-4f8b-b072-1c8819ac454c", "label": "E36N27-12"}, "ID": "3301b28f-8777-4d32-9404-ae615b83b57e", "MissingFields": [], "Role": {"id": "20b1a4e0-97e1-41f7-b519-124a7317266b", "label": "EAMENA Project Staff"}, "Label": "EAMENA-0284942", "Disturbances": [], "Tiles": [["Archaeological Assessment", 1], ["Assessment Summary", 2], ["Condition Assessment", 2], ["Environment Assessment", 1], ["Geography", 2], ["Geometries", 2], ["Resource Summary", 1]]}, {"Actor": {"id": "90ae76cf-865d-4e68-971c-c2b2af9be18c", "label": "Michael Fradley"}, "AddedToDatabase": "2026-05-11", "Country": {"id": "15db88c0-04a2-4c80-9973-076572711d7a", "label": "Saudi Arabia"}, "Date": "2026-04-24", "Grid": {"id": "ff291798-aaa7-4f8b-b072-1c8819ac454c", "label": "E36N27-12"}, "ID": "36574d4e-ef97-40ea-a387-639d16c74111", "MissingFields": [], "Role": {"id": "20b1a4e0-97e1-41f7-b519-124a7317266b", "label": "EAMENA Project Staff"}, "Label": "EAMENA-0284961", "Disturbances": [], "Tiles": [["Archaeological Assessment", 1], ["Assessment Summary", 2], ["Condition Assessment", 2], ["Environment Assessment", 1], ["Geography", 2], ["Geometries", 2], ["Resource Summary", 1]]}, {"Actor": {"id": "90ae76cf-865d-4e68-971c-c2b2af9be18c", "label": "Michael Fradley"}, "AddedToDatabase": "2026-05-11", "Country": {"id": "15db88c0-04a2-4c80-9973-076572711d7a", "label": "Saudi Arabia"}, "Date": "2026-04-24", "Grid": {"id": "ff291798-aaa7-4f8b-b072-1c8819ac454c", "label": "E36N27-12"}, "ID": "55338084-ef19-48f3-af78-5e64a1649674", "MissingFields": [], "Role": {"id": "20b1a4e0-97e1-41f7-b519-124a7317266b", "label": "EAMENA Project Staff"}, "Label": "EAMENA-0284947", "Disturbances": [], "Tiles": [["Archaeological Assessment", 1], ["Assessment Summary", 2], ["Condition Assessment", 2], ["Environment Assessment", 1], ["Geography", 2], ["Geometries", 2], ["Resource Summary", 1]]}, {"Actor": {"id": "90ae76cf-865d-4e68-971c-c2b2af9be18c", "label": "Michael Fradley"}, "AddedToDatabase": "2026-05-11", "Country": {"id": "15db88c0-04a2-4c80-9973-076572711d7a", "label": "Saudi Arabia"}, "Date": "2026-04-24", "Grid": {"id": "ff291798-aaa7-4f8b-b072-1c8819ac454c", "label": "E36N27-12"}, "ID": "580791e1-863c-4854-ba79-b6954133c541", "MissingFields": [], "Role": {"id": "20b1a4e0-97e1-41f7-b519-124a7317266b", "label": "EAMENA Project Staff"}, "Label": "EAMENA-0284963", "Disturbances": [], "Tiles": [["Archaeological Assessment", 1], ["Assessment Summary", 2], ["Condition Assessment", 2], ["Environment Assessment", 1], ["Geography", 2], ["Geometries", 2], ["Resource Summary", 1]]}, {"Actor": {"id": "90ae76cf-865d-4e68-971c-c2b2af9be18c", "label": "Michael Fradley"}, "AddedToDatabase": "2026-05-11", "Country": {"id": "15db88c0-04a2-4c80-9973-076572711d7a", "label": "Saudi Arabia"}, "Date": "2026-04-24", "Grid": {"id": "ff291798-aaa7-4f8b-b072-1c8819ac454c", "label": "E36N27-12"}, "ID": "5a400850-c919-4686-a4bb-d86c89c0a685", "MissingFields": [], "Role": {"id": "20b1a4e0-97e1-41f7-b519-124a7317266b", "label": "EAMENA Project Staff"}, "Label": "EAMENA-0284946", "Disturbances": [], "Tiles": [["Archaeological Assessment", 1], ["Assessment Summary", 2], ["Condition Assessment", 2], ["Environment Assessment", 1], ["Geography", 2], ["Geometries", 2], ["Resource Summary", 1]]}, {"Actor": {"id": "90ae76cf-865d-4e68-971c-c2b2af9be18c", "label": "Michael Fradley"}, "AddedToDatabase": "2026-05-11", "Country": {"id": "15db88c0-04a2-4c80-9973-076572711d7a", "label": "Saudi Arabia"}, "Date": "2026-04-24", "Grid": {"id": "ff291798-aaa7-4f8b-b072-1c8819ac454c", "label": "E36N27-12"}, "ID": "6aed6852-93a1-4bff-9d30-50fcd72bf89c", "MissingFields": [], "Role": {"id": "20b1a4e0-97e1-41f7-b519-124a7317266b", "label": "EAMENA Project Staff"}, "Label": "EAMENA-0284957", "Disturbances": [], "Tiles": [["Archaeological Assessment", 1], ["Assessment Summary", 2], ["Condition Assessment", 2], ["Environment Assessment", 1], ["Geography", 2], ["Geometries", 2], ["Resource Summary", 1]]}, {"Actor": {"id": "90ae76cf-865d-4e68-971c-c2b2af9be18c", "label": "Michael Fradley"}, "AddedToDatabase": "2026-05-11", "Country": {"id": "15db88c0-04a2-4c80-9973-076572711d7a", "label": "Saudi Arabia"}, "Date": "2026-04-24", "Grid": {"id": "ff291798-aaa7-4f8b-b072-1c8819ac454c", "label": "E36N27-12"}, "ID": "72e1962d-23e5-41b1-b84e-eb9c9b317bee", "MissingFields": [], "Role": {"id": "20b1a4e0-97e1-41f7-b519-124a7317266b", "label": "EAMENA Project Staff"}, "Label": "EAMENA-0284954", "Disturbances": [], "Tiles": [["Archaeological Assessment", 1], ["Assessment Summary", 2], ["Condition Assessment", 2], ["Environment Assessment", 1], ["Geography", 2], ["Geometries", 2], ["Resource Summary", 1]]}, {"Actor": {"id": "90ae76cf-865d-4e68-971c-c2b2af9be18c", "label": "Michael Fradley"}, "AddedToDatabase": "2026-05-11", "Country": {"id": "15db88c0-04a2-4c80-9973-076572711d7a", "label": "Saudi Arabia"}, "Date": "2026-04-24", "Grid": {"id": "ff291798-aaa7-4f8b-b072-1c8819ac454c", "label": "E36N27-12"}, "ID": "73bf0446-6657-419c-9cea-11bfcd01640e", "MissingFields": [], "Role": {"id": "20b1a4e0-97e1-41f7-b519-124a7317266b", "label": "EAMENA Project Staff"}, "Label": "EAMENA-0284936", "Disturbances": [], "Tiles": [["Archaeological Assessment", 1], ["Assessment Summary", 2], ["Condition Assessment", 2], ["Environment Assessment", 1], ["Geography", 2], ["Geometries", 2], ["Resource Summary", 1]]}, {"Actor": {"id": "90ae76cf-865d-4e68-971c-c2b2af9be18c", "label": "Michael Fradley"}, "AddedToDatabase": "2026-05-11", "Country": {"id": "15db88c0-04a2-4c80-9973-076572711d7a", "label": "Saudi Arabia"}, "Date": "2026-04-24", "Grid": {"id": "ff291798-aaa7-4f8b-b072-1c8819ac454c", "label": "E36N27-12"}, "ID": "75aba21e-f1bc-44bb-b8f1-c609386e32dd", "MissingFields": [], "Role": {"id": "20b1a4e0-97e1-41f7-b519-124a7317266b", "label": "EAMENA Project Staff"}, "Label": "EAMENA-0284950", "Disturbances": [], "Tiles": [["Archaeological Assessment", 1], ["Assessment Summary", 2], ["Condition Assessment", 2], ["Environment Assessment", 1], ["Geography", 2], ["Geometries", 2], ["Resource Summary", 1]]}, {"Actor": {"id": "90ae76cf-865d-4e68-971c-c2b2af9be18c", "label": "Michael Fradley"}, "AddedToDatabase": "2026-05-11", "Country": {"id": "15db88c0-04a2-4c80-9973-076572711d7a", "label": "Saudi Arabia"}, "Date": "2026-04-24", "Grid": {"id": "ff291798-aaa7-4f8b-b072-1c8819ac454c", "label": "E36N27-12"}, "ID": "7ce6742c-5090-4f17-ba8c-610da4689a9f", "MissingFields": [], "Role": {"id": "20b1a4e0-97e1-41f7-b519-124a7317266b", "label": "EAMENA Project Staff"}, "Label": "EAMENA-0284955", "Disturbances": [], "Tiles": [["Archaeological Assessment", 1], ["Assessment Summary", 2], ["Condition Assessment", 2], ["Environment Assessment", 1], ["Geography", 2], ["Geometries", 2], ["Resource Summary", 1]]}, {"Actor": {"id": "90ae76cf-865d-4e68-971c-c2b2af9be18c", "label": "Michael Fradley"}, "AddedToDatabase": "2026-05-11", "Country": {"id": "15db88c0-04a2-4c80-9973-076572711d7a", "label": "Saudi Arabia"}, "Date": "2026-04-24", "Grid": {"id": "ff291798-aaa7-4f8b-b072-1c8819ac454c", "label": "E36N27-12"}, "ID": "7d4c438a-f235-47cb-bc2d-930eb4d0de46", "MissingFields": [], "Role": {"id": "20b1a4e0-97e1-41f7-b519-124a7317266b", "label": "EAMENA Project Staff"}, "Label": "EAMENA-0284933", "Disturbances": [], "Tiles": [["Archaeological Assessment", 1], ["Assessment Summary", 2], ["Condition Assessment", 2], ["Environment Assessment", 1], ["Geography", 2], ["Geometries", 2], ["Resource Summary", 1]]}, {"Actor": {"id": "90ae76cf-865d-4e68-971c-c2b2af9be18c", "label": "Michael Fradley"}, "AddedToDatabase": "2026-05-11", "Country": {"id": "15db88c0-04a2-4c80-9973-076572711d7a", "label": "Saudi Arabia"}, "Date": "2026-04-24", "Grid": {"id": "ff291798-aaa7-4f8b-b072-1c8819ac454c", "label": "E36N27-12"}, "ID": "80d8c80e-f2c9-4f10-86e4-a66e1315ba7b", "MissingFields": [], "Role": {"id": "20b1a4e0-97e1-41f7-b519-124a7317266b", "label": "EAMENA Project Staff"}, "Label": "EAMENA-0284941", "Disturbances": [], "Tiles": [["Archaeological Assessment", 1], ["Assessment Summary", 2], ["Condition Assessment", 2], ["Environment Assessment", 1], ["Geography", 2], ["Geometries", 2], ["Resource Summary", 1]]}, {"Actor": {"id": "90ae76cf-865d-4e68-971c-c2b2af9be18c", "label": "Michael Fradley"}, "AddedToDatabase": "2026-05-11", "Country": {"id": "15db88c0-04a2-4c80-9973-076572711d7a", "label": "Saudi Arabia"}, "Date": "2026-04-24", "Grid": {"id": "ff291798-aaa7-4f8b-b072-1c8819ac454c", "label": "E36N27-12"}, "ID": "84d347e1-4cf3-4d28-a932-00acbcf5f2b5", "MissingFields": [], "Role": {"id": "20b1a4e0-97e1-41f7-b519-124a7317266b", "label": "EAMENA Project Staff"}, "Label": "EAMENA-0284943", "Disturbances": [], "Tiles": [["Archaeological Assessment", 1], ["Assessment Summary", 2], ["Condition Assessment", 2], ["Environment Assessment", 1], ["Geography", 2], ["Geometries", 2], ["Resource Summary", 1]]}, {"Actor": {"id": "90ae76cf-865d-4e68-971c-c2b2af9be18c", "label": "Michael Fradley"}, "AddedToDatabase": "2026-05-11", "Country": {"id": "15db88c0-04a2-4c80-9973-076572711d7a", "label": "Saudi Arabia"}, "Date": "2026-04-24", "Grid": {"id": "ff291798-aaa7-4f8b-b072-1c8819ac454c", "label": "E36N27-12"}, "ID": "84f08b67-fb1c-4b1a-bacc-1759f320d637", "MissingFields": [], "Role": {"id": "20b1a4e0-97e1-41f7-b519-124a7317266b", "label": "EAMENA Project Staff"}, "Label": "EAMENA-0284949", "Disturbances": [], "Tiles": [["Archaeological Assessment", 1], ["Assessment Summary", 2], ["Condition Assessment", 2], ["Environment Assessment", 1], ["Geography", 2], ["Geometries", 2], ["Resource Summary", 1]]}, {"Actor": {"id": "90ae76cf-865d-4e68-971c-c2b2af9be18c", "label": "Michael Fradley"}, "AddedToDatabase": "2026-05-11", "Country": {"id": "15db88c0-04a2-4c80-9973-076572711d7a", "label": "Saudi Arabia"}, "Date": "2026-04-24", "Grid": {"id": "ff291798-aaa7-4f8b-b072-1c8819ac454c", "label": "E36N27-12"}, "ID": "99ca3a07-8737-4ae1-8f2d-c41f805414fe", "MissingFields": [], "Role": {"id": "20b1a4e0-97e1-41f7-b519-124a7317266b", "label": "EAMENA Project Staff"}, "Label": "EAMENA-0284962", "Disturbances": [], "Tiles": [["Archaeological Assessment", 1], ["Assessment Summary", 2], ["Condition Assessment", 2], ["Environment Assessment", 1], ["Geography", 2], ["Geometries", 2], ["Resource Summary", 1]]}, {"Actor": {"id": "90ae76cf-865d-4e68-971c-c2b2af9be18c", "label": "Michael Fradley"}, "AddedToDatabase": "2026-05-11", "Country": {"id": "15db88c0-04a2-4c80-9973-076572711d7a", "label": "Saudi Arabia"}, "Date": "2026-04-24", "Grid": {"id": "ff291798-aaa7-4f8b-b072-1c8819ac454c", "label": "E36N27-12"}, "ID": "a43b9ffd-025e-4118-883f-3f5f1fb4067e", "MissingFields": [], "Role": {"id": "20b1a4e0-97e1-41f7-b519-124a7317266b", "label": "EAMENA Project Staff"}, "Label": "EAMENA-0284940", "Disturbances": [], "Tiles": [["Archaeological Assessment", 1], ["Assessment Summary", 2], ["Condition Assessment", 2], ["Environment Assessment", 1], ["Geography", 2], ["Geometries", 2], ["Resource Summary", 1]]}, {"Actor": {"id": "90ae76cf-865d-4e68-971c-c2b2af9be18c", "label": "Michael Fradley"}, "AddedToDatabase": "2026-05-11", "Country": {"id": "15db88c0-04a2-4c80-9973-076572711d7a", "label": "Saudi Arabia"}, "Date": "2026-04-24", "Grid": {"id": "ff291798-aaa7-4f8b-b072-1c8819ac454c", "label": "E36N27-12"}, "ID": "a6500013-50d2-48a3-8519-5070782eb5ff", "MissingFields": [], "Role": {"id": "20b1a4e0-97e1-41f7-b519-124a7317266b", "label": "EAMENA Project Staff"}, "Label": "EAMENA-0284956", "Disturbances": [], "Tiles": [["Archaeological Assessment", 1], ["Assessment Summary", 2], ["Condition Assessment", 2], ["Environment Assessment", 1], ["Geography", 2], ["Geometries", 2], ["Resource Summary", 1]]}, {"Actor": {"id": "90ae76cf-865d-4e68-971c-c2b2af9be18c", "label": "Michael Fradley"}, "AddedToDatabase": "2026-05-11", "Country": {"id": "15db88c0-04a2-4c80-9973-076572711d7a", "label": "Saudi Arabia"}, "Date": "2026-04-24", "Grid": {"id": "ff291798-aaa7-4f8b-b072-1c8819ac454c", "label": "E36N27-12"}, "ID": "b8c05520-064b-437e-9ad0-0317b467a04a", "MissingFields": [], "Role": {"id": "20b1a4e0-97e1-41f7-b519-124a7317266b", "label": "EAMENA Project Staff"}, "Label": "EAMENA-0284964", "Disturbances": [], "Tiles": [["Archaeological Assessment", 1], ["Assessment Summary", 2], ["Condition Assessment", 2], ["Environment Assessment", 1], ["Geography", 2], ["Geometries", 2], ["Resource Summary", 1]]}, {"Actor": {"id": "90ae76cf-865d-4e68-971c-c2b2af9be18c", "label": "Michael Fradley"}, "AddedToDatabase": "2026-05-11", "Country": {"id": "15db88c0-04a2-4c80-9973-076572711d7a", "label": "Saudi Arabia"}, "Date": "2026-04-24", "Grid": {"id": "ff291798-aaa7-4f8b-b072-1c8819ac454c", "label": "E36N27-12"}, "ID": "bb6a5517-dcb6-4dc3-956a-aaaccf546b29", "MissingFields": [], "Role": {"id": "20b1a4e0-97e1-41f7-b519-124a7317266b", "label": "EAMENA Project Staff"}, "Label": "EAMENA-0284959", "Disturbances": [], "Tiles": [["Archaeological Assessment", 1], ["Assessment Summary", 2], ["Condition Assessment", 2], ["Environment Assessment", 1], ["Geography", 2], ["Geometries", 2], ["Resource Summary", 1]]}, {"Actor": {"id": "90ae76cf-865d-4e68-971c-c2b2af9be18c", "label": "Michael Fradley"}, "AddedToDatabase": "2026-05-11", "Country": {"id": "15db88c0-04a2-4c80-9973-076572711d7a", "label": "Saudi Arabia"}, "Date": "2026-04-24", "Grid": {"id": "ff291798-aaa7-4f8b-b072-1c8819ac454c", "label": "E36N27-12"}, "ID": "c35f99d8-82b0-47e5-bf5e-9e02789050c6", "MissingFields": [], "Role": {"id": "20b1a4e0-97e1-41f7-b519-124a7317266b", "label": "EAMENA Project Staff"}, "Label": "EAMENA-0284951", "Disturbances": [], "Tiles": [["Archaeological Assessment", 1], ["Assessment Summary", 2], ["Condition Assessment", 2], ["Environment Assessment", 1], ["Geography", 2], ["Geometries", 2], ["Resource Summary", 1]]}, {"Actor": {"id": "90ae76cf-865d-4e68-971c-c2b2af9be18c", "label": "Michael Fradley"}, "AddedToDatabase": "2026-05-11", "Country": {"id": "15db88c0-04a2-4c80-9973-076572711d7a", "label": "Saudi Arabia"}, "Date": "2026-04-24", "Grid": {"id": "ff291798-aaa7-4f8b-b072-1c8819ac454c", "label": "E36N27-12"}, "ID": "ce8bea53-c8cf-41ee-9d53-25b2c11a51f3", "MissingFields": [], "Role": {"id": "20b1a4e0-97e1-41f7-b519-124a7317266b", "label": "EAMENA Project Staff"}, "Label": "EAMENA-0284938", "Disturbances": [], "Tiles": [["Archaeological Assessment", 1], ["Assessment Summary", 2], ["Condition Assessment", 2], ["Environment Assessment", 1], ["Geography", 2], ["Geometries", 2], ["Resource Summary", 1]]}, {"Actor": {"id": "90ae76cf-865d-4e68-971c-c2b2af9be18c", "label": "Michael Fradley"}, "AddedToDatabase": "2026-05-11", "Country": {"id": "15db88c0-04a2-4c80-9973-076572711d7a", "label": "Saudi Arabia"}, "Date": "2026-04-24", "Grid": {"id": "ff291798-aaa7-4f8b-b072-1c8819ac454c", "label": "E36N27-12"}, "ID": "cf1b61ab-e9b0-4d16-890f-473bf3f9b4ba", "MissingFields": [], "Role": {"id": "20b1a4e0-97e1-41f7-b519-124a7317266b", "label": "EAMENA Project Staff"}, "Label": "EAMENA-0284934", "Disturbances": [], "Tiles": [["Archaeological Assessment", 1], ["Assessment Summary", 2], ["Condition Assessment", 2], ["Environment Assessment", 1], ["Geography", 2], ["Geometries", 2], ["Resource Summary", 1]]}, {"Actor": {"id": "90ae76cf-865d-4e68-971c-c2b2af9be18c", "label": "Michael Fradley"}, "AddedToDatabase": "2026-05-11", "Country": {"id": "15db88c0-04a2-4c80-9973-076572711d7a", "label": "Saudi Arabia"}, "Date": "2026-04-24", "Grid": {"id": "ff291798-aaa7-4f8b-b072-1c8819ac454c", "label": "E36N27-12"}, "ID": "d168eafd-13a6-4a07-bbc0-cec85721bac0", "MissingFields": [], "Role": {"id": "20b1a4e0-97e1-41f7-b519-124a7317266b", "label": "EAMENA Project Staff"}, "Label": "EAMENA-0284952", "Disturbances": [], "Tiles": [["Archaeological Assessment", 1], ["Assessment Summary", 2], ["Condition Assessment", 2], ["Environment Assessment", 1], ["Geography", 2], ["Geometries", 2], ["Resource Summary", 1]]}, {"Actor": {"id": "90ae76cf-865d-4e68-971c-c2b2af9be18c", "label": "Michael Fradley"}, "AddedToDatabase": "2026-05-11", "Country": {"id": "15db88c0-04a2-4c80-9973-076572711d7a", "label": "Saudi Arabia"}, "Date": "2026-04-24", "Grid": {"id": "ff291798-aaa7-4f8b-b072-1c8819ac454c", "label": "E36N27-12"}, "ID": "dcdda898-a364-49d3-a8a0-1cb4150d913b", "MissingFields": [], "Role": {"id": "20b1a4e0-97e1-41f7-b519-124a7317266b", "label": "EAMENA Project Staff"}, "Label": "EAMENA-0284937", "Disturbances": [], "Tiles": [["Archaeological Assessment", 1], ["Assessment Summary", 2], ["Condition Assessment", 2], ["Environment Assessment", 1], ["Geography", 2], ["Geometries", 2], ["Resource Summary", 1]]}, {"Actor": {"id": "90ae76cf-865d-4e68-971c-c2b2af9be18c", "label": "Michael Fradley"}, "AddedToDatabase": "2026-05-11", "Country": {"id": "15db88c0-04a2-4c80-9973-076572711d7a", "label": "Saudi Arabia"}, "Date": "2026-04-24", "Grid": {"id": "ff291798-aaa7-4f8b-b072-1c8819ac454c", "label": "E36N27-12"}, "ID": "e13a94cb-c8e3-413d-aa56-5aea5f4d72b4", "MissingFields": [], "Role": {"id": "20b1a4e0-97e1-41f7-b519-124a7317266b", "label": "EAMENA Project Staff"}, "Label": "EAMENA-0284939", "Disturbances": [], "Tiles": [["Archaeological Assessment", 1], ["Assessment Summary", 2], ["Condition Assessment", 2], ["Environment Assessment", 1], ["Geography", 2], ["Geometries", 2], ["Resource Summary", 1]]}]}