[{"Actor": {"id": "90ae76cf-865d-4e68-971c-c2b2af9be18c", "label": "Michael Fradley"}, "AddedToDatabase": "2023-05-03", "Country": {"id": "15db88c0-04a2-4c80-9973-076572711d7a", "label": "Saudi Arabia"}, "Date": "2022-03-18", "Grid": {"id": "6bbfe6ad-3095-4d9f-8f98-289ad496f261", "label": "E42N27-22"}, "ID": "4a3913bd-ad49-4354-9545-74f6fb8d90aa", "Role": {"id": "20b1a4e0-97e1-41f7-b519-124a7317266b", "label": "EAMENA Project Staff"}, "Label": "EAMENA-0200388", "Tiles": [["Geometry", 1], ["Geometry Location Observation", 1], ["Assessment Activity", 1], ["Condition State", 1], ["Condition Assessment", 1], ["Environment Assessment", 1], ["Modern Country Territory", 1], ["Archaeological Assessment ", 1], ["Resource Summary", 1], ["Assessment Summary", 1], ["Geography", 1]]}, {"Actor": {"id": "90ae76cf-865d-4e68-971c-c2b2af9be18c", "label": "Michael Fradley"}, "AddedToDatabase": "2023-05-03", "Country": {"id": "15db88c0-04a2-4c80-9973-076572711d7a", "label": "Saudi Arabia"}, "Date": "2022-05-25", "Grid": {"id": "6bbfe6ad-3095-4d9f-8f98-289ad496f261", "label": "E42N27-22"}, "ID": "5ea99b56-ef04-42e9-994a-3400e02287f7", "Role": {"id": "20b1a4e0-97e1-41f7-b519-124a7317266b", "label": "EAMENA Project Staff"}, "Label": "EAMENA-0204795", "Tiles": [["Condition State", 1], ["Geometry", 1], ["Resource Summary", 1], ["Geometry Location Observation", 1], ["Modern Country Territory", 1], ["Assessment Summary", 1], ["Condition Assessment", 1], ["Archaeological Assessment ", 1], ["Geography", 1], ["Assessment Activity", 1]]}, {"Actor": {"id": "90ae76cf-865d-4e68-971c-c2b2af9be18c", "label": "Michael Fradley"}, "AddedToDatabase": "2023-05-03", "Country": {"id": "15db88c0-04a2-4c80-9973-076572711d7a", "label": "Saudi Arabia"}, "Date": "2022-03-18", "Grid": {"id": "6bbfe6ad-3095-4d9f-8f98-289ad496f261", "label": "E42N27-22"}, "ID": "6d01b58b-ccd8-472c-bc2c-941b8c705711", "Role": {"id": "20b1a4e0-97e1-41f7-b519-124a7317266b", "label": "EAMENA Project Staff"}, "Label": "EAMENA-0200385", "Tiles": [["Assessment Summary", 1], ["Geography", 1], ["Condition Assessment", 1], ["Geometry Location Observation", 1], ["Resource Summary", 1], ["Condition State", 1], ["Archaeological Assessment ", 1], ["Geometry", 1], ["Environment Assessment", 1], ["Assessment Activity", 1], ["Modern Country Territory", 1]]}, {"Actor": {"id": "90ae76cf-865d-4e68-971c-c2b2af9be18c", "label": "Michael Fradley"}, "AddedToDatabase": "2023-05-03", "Country": {"id": "15db88c0-04a2-4c80-9973-076572711d7a", "label": "Saudi Arabia"}, "Date": "2022-03-18", "Grid": {"id": "6bbfe6ad-3095-4d9f-8f98-289ad496f261", "label": "E42N27-22"}, "ID": "962f95ff-6d90-4d21-b1c0-94040e5ca90e", "Role": {"id": "20b1a4e0-97e1-41f7-b519-124a7317266b", "label": "EAMENA Project Staff"}, "Label": "EAMENA-0200389", "Tiles": [["Environment Assessment", 1], ["Condition Assessment", 1], ["Assessment Activity", 1], ["Geography", 1], ["Modern Country Territory", 1], ["Resource Summary", 1], ["Condition State", 1], ["Geometry Location Observation", 1], ["Archaeological Assessment ", 1], ["Geometry", 1], ["Assessment Summary", 1]]}, {"Actor": {"id": "90ae76cf-865d-4e68-971c-c2b2af9be18c", "label": "Michael Fradley"}, "AddedToDatabase": "2023-05-03", "Country": {"id": "15db88c0-04a2-4c80-9973-076572711d7a", "label": "Saudi Arabia"}, "Date": "2022-03-18", "Grid": {"id": "6bbfe6ad-3095-4d9f-8f98-289ad496f261", "label": "E42N27-22"}, "ID": "99b9e9e9-f4da-4921-8fe4-6f74e1cf68a4", "Role": {"id": "20b1a4e0-97e1-41f7-b519-124a7317266b", "label": "EAMENA Project Staff"}, "Label": "EAMENA-0200386", "Tiles": [["Assessment Activity", 1], ["Assessment Summary", 1], ["Condition Assessment", 1], ["Geometry Location Observation", 1], ["Condition State", 1], ["Resource Summary", 1], ["Geometry", 1], ["Archaeological Assessment ", 1], ["Geography", 1], ["Environment Assessment", 1], ["Modern Country Territory", 1]]}, {"Actor": {"id": "90ae76cf-865d-4e68-971c-c2b2af9be18c", "label": "Michael Fradley"}, "AddedToDatabase": "2023-05-03", "Country": {"id": "15db88c0-04a2-4c80-9973-076572711d7a", "label": "Saudi Arabia"}, "Date": "2022-03-18", "Grid": {"id": "6bbfe6ad-3095-4d9f-8f98-289ad496f261", "label": "E42N27-22"}, "ID": "fcb14241-d172-44e9-b748-5bd8259819ca", "Role": {"id": "20b1a4e0-97e1-41f7-b519-124a7317266b", "label": "EAMENA Project Staff"}, "Label": "EAMENA-0200387", "Tiles": [["Geometry", 1], ["Assessment Activity", 1], ["Environment Assessment", 1], ["Modern Country Territory", 1], ["Assessment Summary", 1], ["Geometry Location Observation", 1], ["Geography", 1], ["Condition Assessment", 1], ["Resource Summary", 1], ["Condition State", 1], ["Archaeological Assessment ", 1]]}]