[{"AddedToDatabase": "2023-05-01", "Country": {"id": "f635aa2f-6b00-4d7d-b215-33f6256b6350", "label": "Iraq"}, "Date": "2023-05-01", "Grid": {"id": "6ea85f2f-1b06-436a-bfd7-525afbe17263", "label": "E45N31-44"}, "ID": "043847eb-69c9-408c-9619-39b86824209e", "Label": "EAMENA-0077982", "Tiles": [["Archaeological Assessment ", 1], ["Condition State", 1], ["Geometry", 1], ["Geometry Location Observation", 1], ["Condition Assessment", 1], ["Modern Country Territory", 1], ["Resource Summary", 1], ["Geography", 1]]}, {"AddedToDatabase": "2023-05-01", "Country": {"id": "f635aa2f-6b00-4d7d-b215-33f6256b6350", "label": "Iraq"}, "Date": "2023-05-01", "Grid": {"id": "6ea85f2f-1b06-436a-bfd7-525afbe17263", "label": "E45N31-44"}, "ID": "04de4d08-cd27-4682-bbd4-009cf3e745ea", "Label": "EAMENA-0077991", "Tiles": [["Condition Assessment", 1], ["Resource Summary", 1], ["Modern Country Territory", 1], ["Geography", 1], ["Archaeological Assessment ", 1], ["Geometry", 1], ["Condition State", 1], ["Geometry Location Observation", 1]]}, {"AddedToDatabase": "2023-05-01", "Country": {"id": "f635aa2f-6b00-4d7d-b215-33f6256b6350", "label": "Iraq"}, "Date": "2023-05-01", "Grid": {"id": "6ea85f2f-1b06-436a-bfd7-525afbe17263", "label": "E45N31-44"}, "ID": "09412595-4b0a-4107-b7f6-145c7c44d901", "Label": "EAMENA-0077949", "Tiles": [["Condition Assessment", 1], ["Resource Summary", 1], ["Geometry Location Observation", 1], ["Archaeological Assessment ", 1], ["Condition State", 1], ["Modern Country Territory", 1], ["Geography", 1], ["Geometry", 1]]}, {"AddedToDatabase": "2023-05-01", "Country": {"id": "f635aa2f-6b00-4d7d-b215-33f6256b6350", "label": "Iraq"}, "Date": "2023-05-01", "Grid": {"id": "6ea85f2f-1b06-436a-bfd7-525afbe17263", "label": "E45N31-44"}, "ID": "0b5ec790-e474-4421-922d-c57c09dfc72e", "Label": "EAMENA-0077951", "Tiles": [["Condition Assessment", 1], ["Resource Summary", 1], ["Geometry Location Observation", 1], ["Geometry", 1], ["Archaeological Assessment ", 1], ["Modern Country Territory", 1], ["Geography", 1], ["Condition State", 1]]}, {"AddedToDatabase": "2023-05-01", "Country": {"id": "f635aa2f-6b00-4d7d-b215-33f6256b6350", "label": "Iraq"}, "Date": "2023-05-01", "Grid": {"id": "6ea85f2f-1b06-436a-bfd7-525afbe17263", "label": "E45N31-44"}, "ID": "0b98c6f9-65c2-48e3-8158-4beda3ad81d7", "Label": "EAMENA-0077944", "Tiles": [["Geometry Location Observation", 1], ["Modern Country Territory", 1], ["Geometry", 1], ["Resource Summary", 1], ["Condition Assessment", 1], ["Condition State", 1], ["Archaeological Assessment ", 1], ["Geography", 1]]}, {"AddedToDatabase": "2023-05-01", "Country": {"id": "f635aa2f-6b00-4d7d-b215-33f6256b6350", "label": "Iraq"}, "Date": "2023-05-01", "Grid": {"id": "6ea85f2f-1b06-436a-bfd7-525afbe17263", "label": "E45N31-44"}, "ID": "0e42fa20-91a2-4af2-b4a7-3389821f12ed", "Label": "EAMENA-0077970", "Tiles": [["Archaeological Assessment ", 1], ["Condition State", 1], ["Geography", 1], ["Modern Country Territory", 1], ["Resource Summary", 1], ["Geometry", 1], ["Geometry Location Observation", 1], ["Condition Assessment", 1]]}, {"AddedToDatabase": "2023-05-01", "Country": {"id": "f635aa2f-6b00-4d7d-b215-33f6256b6350", "label": "Iraq"}, "Date": "2023-05-01", "Grid": {"id": "6ea85f2f-1b06-436a-bfd7-525afbe17263", "label": "E45N31-44"}, "ID": "0e62f296-a221-4133-88b1-58e2bee6ee2f", "Label": "EAMENA-0077967", "Tiles": [["Archaeological Assessment ", 1], ["Condition State", 1], ["Geometry Location Observation", 1], ["Geography", 1], ["Condition Assessment", 1], ["Modern Country Territory", 1], ["Geometry", 1], ["Resource Summary", 1]]}, {"AddedToDatabase": "2023-05-01", "Country": {"id": "f635aa2f-6b00-4d7d-b215-33f6256b6350", "label": "Iraq"}, "Date": "2023-05-01", "Grid": {"id": "6ea85f2f-1b06-436a-bfd7-525afbe17263", "label": "E45N31-44"}, "ID": "32f669f7-66c0-418d-83d8-97d12ac2dd9b", "Label": "EAMENA-0077966", "Tiles": [["Condition Assessment", 1], ["Condition State", 1], ["Geography", 1], ["Geometry Location Observation", 1], ["Geometry", 1], ["Archaeological Assessment ", 1], ["Resource Summary", 1], ["Modern Country Territory", 1]]}, {"AddedToDatabase": "2023-05-01", "Country": {"id": "f635aa2f-6b00-4d7d-b215-33f6256b6350", "label": "Iraq"}, "Date": "2023-05-01", "Grid": {"id": "6ea85f2f-1b06-436a-bfd7-525afbe17263", "label": "E45N31-44"}, "ID": "37f1d7a9-002b-4ee2-bf40-2781d089ca55", "Label": "EAMENA-0077988", "Tiles": [["Geometry Location Observation", 1], ["Resource Summary", 1], ["Condition Assessment", 1], ["Condition State", 1], ["Geography", 1], ["Modern Country Territory", 1], ["Geometry", 1], ["Archaeological Assessment ", 1]]}, {"AddedToDatabase": "2023-05-01", "Country": {"id": "f635aa2f-6b00-4d7d-b215-33f6256b6350", "label": "Iraq"}, "Date": "2023-05-01", "Grid": {"id": "6ea85f2f-1b06-436a-bfd7-525afbe17263", "label": "E45N31-44"}, "ID": "3a3b6fc8-b1ee-4dd0-b51a-a94435b06690", "Label": "EAMENA-0077962", "Tiles": [["Geography", 1], ["Geometry", 1], ["Modern Country Territory", 1], ["Archaeological Assessment ", 1], ["Resource Summary", 1], ["Geometry Location Observation", 1], ["Condition Assessment", 1], ["Condition State", 1]]}, {"AddedToDatabase": "2023-05-01", "Country": {"id": "f635aa2f-6b00-4d7d-b215-33f6256b6350", "label": "Iraq"}, "Date": "2023-05-01", "Grid": {"id": "6ea85f2f-1b06-436a-bfd7-525afbe17263", "label": "E45N31-44"}, "ID": "3c641f56-7ac7-4035-a660-b9233994af83", "Label": "EAMENA-0077990", "Tiles": [["Condition Assessment", 1], ["Modern Country Territory", 1], ["Geometry", 1], ["Condition State", 1], ["Archaeological Assessment ", 1], ["Geometry Location Observation", 1], ["Geography", 1], ["Resource Summary", 1]]}, {"AddedToDatabase": "2023-05-01", "Country": {"id": "f635aa2f-6b00-4d7d-b215-33f6256b6350", "label": "Iraq"}, "Date": "2023-05-01", "Grid": {"id": "6ea85f2f-1b06-436a-bfd7-525afbe17263", "label": "E45N31-44"}, "ID": "3c8af23c-c122-4476-903d-52c0ad40bf59", "Label": "EAMENA-0077997", "Tiles": [["Modern Country Territory", 1], ["Archaeological Assessment ", 1], ["Condition State", 1], ["Geography", 1], ["Geometry", 1], ["Geometry Location Observation", 1], ["Resource Summary", 1], ["Condition Assessment", 1]]}, {"AddedToDatabase": "2023-05-01", "Country": {"id": "f635aa2f-6b00-4d7d-b215-33f6256b6350", "label": "Iraq"}, "Date": "2023-05-01", "Grid": {"id": "6ea85f2f-1b06-436a-bfd7-525afbe17263", "label": "E45N31-44"}, "ID": "51988179-de91-497b-bc11-80b711010dfe", "Label": "EAMENA-0077993", "Tiles": [["Geometry", 1], ["Condition State", 1], ["Archaeological Assessment ", 1], ["Condition Assessment", 1], ["Geometry Location Observation", 1], ["Geography", 1], ["Modern Country Territory", 1], ["Resource Summary", 1]]}, {"AddedToDatabase": "2023-05-01", "Country": {"id": "f635aa2f-6b00-4d7d-b215-33f6256b6350", "label": "Iraq"}, "Date": "2023-05-01", "Grid": {"id": "6ea85f2f-1b06-436a-bfd7-525afbe17263", "label": "E45N31-44"}, "ID": "56b58300-621f-4240-bc59-bbf506169b50", "Label": "EAMENA-0077948", "Tiles": [["Geometry Location Observation", 1], ["Archaeological Assessment ", 1], ["Geography", 1], ["Condition Assessment", 1], ["Modern Country Territory", 1], ["Resource Summary", 1], ["Geometry", 1], ["Condition State", 1]]}, {"AddedToDatabase": "2023-05-01", "Country": {"id": "f635aa2f-6b00-4d7d-b215-33f6256b6350", "label": "Iraq"}, "Date": "2023-05-01", "Grid": {"id": "6ea85f2f-1b06-436a-bfd7-525afbe17263", "label": "E45N31-44"}, "ID": "64a61fb5-ef2c-46e4-b6b0-e62fdfef1739", "Label": "EAMENA-0078002", "Tiles": [["Geometry", 1], ["Modern Country Territory", 1], ["Resource Summary", 1], ["Geometry Location Observation", 1], ["Condition State", 1], ["Geography", 1], ["Archaeological Assessment ", 1], ["Condition Assessment", 1]]}, {"AddedToDatabase": "2023-05-01", "Country": {"id": "f635aa2f-6b00-4d7d-b215-33f6256b6350", "label": "Iraq"}, "Date": "2023-05-01", "Grid": {"id": "6ea85f2f-1b06-436a-bfd7-525afbe17263", "label": "E45N31-44"}, "ID": "69479418-c5e2-44fb-ac93-86f4dd680e36", "Label": "EAMENA-0077957", "Tiles": [["Geography", 1], ["Modern Country Territory", 1], ["Condition State", 1], ["Resource Summary", 1], ["Archaeological Assessment ", 1], ["Condition Assessment", 1], ["Geometry", 1], ["Geometry Location Observation", 1]]}, {"AddedToDatabase": "2023-05-01", "Country": {"id": "f635aa2f-6b00-4d7d-b215-33f6256b6350", "label": "Iraq"}, "Date": "2023-05-01", "Grid": {"id": "6ea85f2f-1b06-436a-bfd7-525afbe17263", "label": "E45N31-44"}, "ID": "69ea347c-3dbb-4f6d-a911-e5cea05bd230", "Label": "EAMENA-0077969", "Tiles": [["Geometry Location Observation", 1], ["Geography", 1], ["Archaeological Assessment ", 1], ["Resource Summary", 1], ["Geometry", 1], ["Condition Assessment", 1], ["Condition State", 1], ["Modern Country Territory", 1]]}, {"AddedToDatabase": "2023-05-01", "Country": {"id": "f635aa2f-6b00-4d7d-b215-33f6256b6350", "label": "Iraq"}, "Date": "2023-05-01", "Grid": {"id": "6ea85f2f-1b06-436a-bfd7-525afbe17263", "label": "E45N31-44"}, "ID": "6c422c1e-c848-43dd-a4ef-743d7718dffc", "Label": "EAMENA-0077959", "Tiles": [["Archaeological Assessment ", 1], ["Resource Summary", 1], ["Geography", 1], ["Modern Country Territory", 1], ["Condition Assessment", 1], ["Geometry Location Observation", 1], ["Condition State", 1], ["Geometry", 1]]}, {"AddedToDatabase": "2023-05-01", "Country": {"id": "f635aa2f-6b00-4d7d-b215-33f6256b6350", "label": "Iraq"}, "Date": "2023-05-01", "Grid": {"id": "6ea85f2f-1b06-436a-bfd7-525afbe17263", "label": "E45N31-44"}, "ID": "6cdb3cf7-9889-408e-98a0-286dd83c26d6", "Label": "EAMENA-0077998", "Tiles": [["Condition State", 1], ["Archaeological Assessment ", 1], ["Resource Summary", 1], ["Modern Country Territory", 1], ["Geography", 1], ["Condition Assessment", 1], ["Geometry Location Observation", 1], ["Geometry", 1]]}, {"AddedToDatabase": "2023-05-01", "Country": {"id": "f635aa2f-6b00-4d7d-b215-33f6256b6350", "label": "Iraq"}, "Date": "2023-05-01", "Grid": {"id": "6ea85f2f-1b06-436a-bfd7-525afbe17263", "label": "E45N31-44"}, "ID": "76495058-899d-4db1-be65-92e3283db50d", "Label": "EAMENA-0078005", "Tiles": [["Resource Summary", 1], ["Geometry", 1], ["Geometry Location Observation", 1], ["Archaeological Assessment ", 1], ["Condition Assessment", 1], ["Condition State", 1], ["Modern Country Territory", 1], ["Geography", 1]]}, {"AddedToDatabase": "2023-05-01", "Country": {"id": "f635aa2f-6b00-4d7d-b215-33f6256b6350", "label": "Iraq"}, "Date": "2023-05-01", "Grid": {"id": "6ea85f2f-1b06-436a-bfd7-525afbe17263", "label": "E45N31-44"}, "ID": "7764150f-9cf8-42e4-bcc3-4e09146c8ffc", "Label": "EAMENA-0077955", "Tiles": [["Archaeological Assessment ", 1], ["Resource Summary", 1], ["Modern Country Territory", 1], ["Geometry Location Observation", 1], ["Condition Assessment", 1], ["Geometry", 1], ["Condition State", 1], ["Geography", 1]]}, {"AddedToDatabase": "2023-05-01", "Country": {"id": "f635aa2f-6b00-4d7d-b215-33f6256b6350", "label": "Iraq"}, "Date": "2023-05-01", "Grid": {"id": "6ea85f2f-1b06-436a-bfd7-525afbe17263", "label": "E45N31-44"}, "ID": "77885711-dea4-4a0d-8ffc-b72b61ab3313", "Label": "EAMENA-0078007", "Tiles": [["Geometry Location Observation", 1], ["Condition State", 1], ["Modern Country Territory", 1], ["Geography", 1], ["Archaeological Assessment ", 1], ["Resource Summary", 1], ["Geometry", 1], ["Condition Assessment", 1]]}, {"AddedToDatabase": "2023-05-01", "Country": {"id": "f635aa2f-6b00-4d7d-b215-33f6256b6350", "label": "Iraq"}, "Date": "2023-05-01", "Grid": {"id": "6ea85f2f-1b06-436a-bfd7-525afbe17263", "label": "E45N31-44"}, "ID": "837f3fcf-923f-46a9-8349-d6244a2a81b9", "Label": "EAMENA-0077995", "Tiles": [["Geometry Location Observation", 1], ["Condition Assessment", 1], ["Modern Country Territory", 1], ["Geometry", 1], ["Condition State", 1], ["Resource Summary", 1], ["Archaeological Assessment ", 1], ["Geography", 1]]}, {"AddedToDatabase": "2023-05-01", "Country": {"id": "f635aa2f-6b00-4d7d-b215-33f6256b6350", "label": "Iraq"}, "Date": "2023-05-01", "Grid": {"id": "6ea85f2f-1b06-436a-bfd7-525afbe17263", "label": "E45N31-44"}, "ID": "8e9b76e2-542c-486f-9b9b-a33dc8103994", "Label": "EAMENA-0078008", "Tiles": [["Resource Summary", 1], ["Condition Assessment", 1], ["Condition State", 1], ["Geometry", 1], ["Archaeological Assessment ", 1], ["Geography", 1], ["Modern Country Territory", 1], ["Geometry Location Observation", 1]]}, {"AddedToDatabase": "2023-05-01", "Country": {"id": "f635aa2f-6b00-4d7d-b215-33f6256b6350", "label": "Iraq"}, "Date": "2023-05-01", "Grid": {"id": "6ea85f2f-1b06-436a-bfd7-525afbe17263", "label": "E45N31-44"}, "ID": "8fdbff4e-e390-474d-81c2-9f89c63b243a", "Label": "EAMENA-0077992", "Tiles": [["Archaeological Assessment ", 1], ["Geography", 1], ["Geometry Location Observation", 1], ["Geometry", 1], ["Resource Summary", 1], ["Modern Country Territory", 1], ["Condition State", 1], ["Condition Assessment", 1]]}, {"AddedToDatabase": "2023-05-01", "Country": {"id": "f635aa2f-6b00-4d7d-b215-33f6256b6350", "label": "Iraq"}, "Date": "2023-05-01", "Grid": {"id": "6ea85f2f-1b06-436a-bfd7-525afbe17263", "label": "E45N31-44"}, "ID": "99df36fe-c50d-46e6-a1a0-7fa0692794f7", "Label": "EAMENA-0077999", "Tiles": [["Geography", 1], ["Modern Country Territory", 1], ["Geometry Location Observation", 1], ["Condition State", 1], ["Resource Summary", 1], ["Geometry", 1], ["Condition Assessment", 1], ["Archaeological Assessment ", 1]]}, {"AddedToDatabase": "2023-05-01", "Country": {"id": "f635aa2f-6b00-4d7d-b215-33f6256b6350", "label": "Iraq"}, "Date": "2023-05-01", "Grid": {"id": "6ea85f2f-1b06-436a-bfd7-525afbe17263", "label": "E45N31-44"}, "ID": "a3c1fd4a-279e-4f9a-961c-c78d92770afc", "Label": "EAMENA-0077978", "Tiles": [["Geometry Location Observation", 1], ["Condition State", 1], ["Geography", 1], ["Modern Country Territory", 1], ["Geometry", 1], ["Resource Summary", 1], ["Archaeological Assessment ", 1], ["Condition Assessment", 1]]}, {"AddedToDatabase": "2023-05-01", "Country": {"id": "f635aa2f-6b00-4d7d-b215-33f6256b6350", "label": "Iraq"}, "Date": "2023-05-01", "Grid": {"id": "6ea85f2f-1b06-436a-bfd7-525afbe17263", "label": "E45N31-44"}, "ID": "a410f7c3-d27a-4a74-9582-60b2dd914362", "Label": "EAMENA-0077943", "Tiles": [["Archaeological Assessment ", 1], ["Geometry Location Observation", 1], ["Geography", 1], ["Condition Assessment", 1], ["Resource Summary", 1], ["Modern Country Territory", 1], ["Condition State", 1], ["Geometry", 1]]}, {"AddedToDatabase": "2023-05-01", "Country": {"id": "f635aa2f-6b00-4d7d-b215-33f6256b6350", "label": "Iraq"}, "Date": "2023-05-01", "Grid": {"id": "6ea85f2f-1b06-436a-bfd7-525afbe17263", "label": "E45N31-44"}, "ID": "a51edaca-104a-41d4-8552-ad364b2e0fd5", "Label": "EAMENA-0077973", "Tiles": [["Geometry Location Observation", 1], ["Condition Assessment", 1], ["Geometry", 1], ["Modern Country Territory", 1], ["Geography", 1], ["Condition State", 1], ["Resource Summary", 1], ["Archaeological Assessment ", 1]]}, {"AddedToDatabase": "2023-05-01", "Country": {"id": "f635aa2f-6b00-4d7d-b215-33f6256b6350", "label": "Iraq"}, "Date": "2023-05-01", "Grid": {"id": "6ea85f2f-1b06-436a-bfd7-525afbe17263", "label": "E45N31-44"}, "ID": "a648e724-18a8-402c-995f-33dd6a0cd876", "Label": "EAMENA-0077989", "Tiles": [["Geometry Location Observation", 1], ["Geography", 1], ["Resource Summary", 1], ["Modern Country Territory", 1], ["Condition Assessment", 1], ["Archaeological Assessment ", 1], ["Geometry", 1], ["Condition State", 1]]}, {"AddedToDatabase": "2023-05-01", "Country": {"id": "f635aa2f-6b00-4d7d-b215-33f6256b6350", "label": "Iraq"}, "Date": "2023-05-01", "Grid": {"id": "6ea85f2f-1b06-436a-bfd7-525afbe17263", "label": "E45N31-44"}, "ID": "a8834749-cc3d-438d-83bb-0fbec3f72fa0", "Label": "EAMENA-0077971", "Tiles": [["Geometry Location Observation", 1], ["Modern Country Territory", 1], ["Geometry", 1], ["Condition State", 1], ["Geography", 1], ["Archaeological Assessment ", 1], ["Condition Assessment", 1], ["Resource Summary", 1]]}, {"AddedToDatabase": "2023-05-01", "Country": {"id": "f635aa2f-6b00-4d7d-b215-33f6256b6350", "label": "Iraq"}, "Date": "2023-05-01", "Grid": {"id": "6ea85f2f-1b06-436a-bfd7-525afbe17263", "label": "E45N31-44"}, "ID": "a8e52eda-386c-4854-8269-0592242eb6fa", "Label": "EAMENA-0077980", "Tiles": [["Modern Country Territory", 1], ["Condition Assessment", 1], ["Geometry", 1], ["Geometry Location Observation", 1], ["Geography", 1], ["Resource Summary", 1], ["Archaeological Assessment ", 1], ["Condition State", 1]]}, {"AddedToDatabase": "2023-05-01", "Country": {"id": "f635aa2f-6b00-4d7d-b215-33f6256b6350", "label": "Iraq"}, "Date": "2023-05-01", "Grid": {"id": "6ea85f2f-1b06-436a-bfd7-525afbe17263", "label": "E45N31-44"}, "ID": "ae4ac4d2-8d3a-40e4-9efb-44410e4326d5", "Label": "EAMENA-0077994", "Tiles": [["Condition Assessment", 1], ["Condition State", 1], ["Modern Country Territory", 1], ["Geometry Location Observation", 1], ["Geography", 1], ["Resource Summary", 1], ["Geometry", 1], ["Archaeological Assessment ", 1]]}, {"AddedToDatabase": "2023-05-01", "Country": {"id": "f635aa2f-6b00-4d7d-b215-33f6256b6350", "label": "Iraq"}, "Date": "2023-05-01", "Grid": {"id": "6ea85f2f-1b06-436a-bfd7-525afbe17263", "label": "E45N31-44"}, "ID": "aeea2536-56e7-486f-8a5d-3789bc655968", "Label": "EAMENA-0077953", "Tiles": [["Geometry", 1], ["Geography", 1], ["Resource Summary", 1], ["Modern Country Territory", 1], ["Geometry Location Observation", 1], ["Archaeological Assessment ", 1], ["Condition Assessment", 1], ["Condition State", 1]]}, {"AddedToDatabase": "2023-05-01", "Country": {"id": "f635aa2f-6b00-4d7d-b215-33f6256b6350", "label": "Iraq"}, "Date": "2023-05-01", "Grid": {"id": "6ea85f2f-1b06-436a-bfd7-525afbe17263", "label": "E45N31-44"}, "ID": "b429aca3-ae61-42fa-a0e0-b3e3a130e2b8", "Label": "EAMENA-0077968", "Tiles": [["Geometry Location Observation", 1], ["Archaeological Assessment ", 1], ["Condition Assessment", 1], ["Geometry", 1], ["Resource Summary", 1], ["Modern Country Territory", 1], ["Geography", 1], ["Condition State", 1]]}, {"AddedToDatabase": "2023-05-01", "Country": {"id": "f635aa2f-6b00-4d7d-b215-33f6256b6350", "label": "Iraq"}, "Date": "2023-05-01", "Grid": {"id": "6ea85f2f-1b06-436a-bfd7-525afbe17263", "label": "E45N31-44"}, "ID": "b78258a7-cf94-4212-a8b3-fadc009ea935", "Label": "EAMENA-0077983", "Tiles": [["Geography", 1], ["Condition State", 1], ["Resource Summary", 1], ["Geometry Location Observation", 1], ["Condition Assessment", 1], ["Archaeological Assessment ", 1], ["Geometry", 1], ["Modern Country Territory", 1]]}, {"AddedToDatabase": "2023-05-01", "Country": {"id": "f635aa2f-6b00-4d7d-b215-33f6256b6350", "label": "Iraq"}, "Date": "2023-05-01", "Grid": {"id": "6ea85f2f-1b06-436a-bfd7-525afbe17263", "label": "E45N31-44"}, "ID": "b897ef66-7a12-4889-bfdf-36abd9c3c799", "Label": "EAMENA-0077958", "Tiles": [["Resource Summary", 1], ["Archaeological Assessment ", 1], ["Modern Country Territory", 1], ["Geometry", 1], ["Geometry Location Observation", 1], ["Condition Assessment", 1], ["Geography", 1], ["Condition State", 1]]}, {"AddedToDatabase": "2023-05-01", "Country": {"id": "f635aa2f-6b00-4d7d-b215-33f6256b6350", "label": "Iraq"}, "Date": "2023-05-01", "Grid": {"id": "6ea85f2f-1b06-436a-bfd7-525afbe17263", "label": "E45N31-44"}, "ID": "bf65adf6-c011-4cfa-9f6f-402f8213e4d4", "Label": "EAMENA-0077981", "Tiles": [["Geometry", 1], ["Archaeological Assessment ", 1], ["Condition Assessment", 1], ["Modern Country Territory", 1], ["Resource Summary", 1], ["Condition State", 1], ["Geometry Location Observation", 1], ["Geography", 1]]}, {"AddedToDatabase": "2023-05-01", "Country": {"id": "f635aa2f-6b00-4d7d-b215-33f6256b6350", "label": "Iraq"}, "Date": "2023-05-01", "Grid": {"id": "6ea85f2f-1b06-436a-bfd7-525afbe17263", "label": "E45N31-44"}, "ID": "c92d97d2-24c2-46f8-98bc-b314567f527b", "Label": "EAMENA-0077984", "Tiles": [["Geometry", 1], ["Condition Assessment", 1], ["Geography", 1], ["Resource Summary", 1], ["Modern Country Territory", 1], ["Archaeological Assessment ", 1], ["Condition State", 1], ["Geometry Location Observation", 1]]}, {"AddedToDatabase": "2023-05-01", "Country": {"id": "f635aa2f-6b00-4d7d-b215-33f6256b6350", "label": "Iraq"}, "Date": "2023-05-01", "Grid": {"id": "6ea85f2f-1b06-436a-bfd7-525afbe17263", "label": "E45N31-44"}, "ID": "d2a48b26-70b9-4c05-8b3f-8a71bb788bcd", "Label": "EAMENA-0077961", "Tiles": [["Archaeological Assessment ", 1], ["Geography", 1], ["Condition State", 1], ["Geometry", 1], ["Modern Country Territory", 1], ["Resource Summary", 1], ["Geometry Location Observation", 1], ["Condition Assessment", 1]]}, {"AddedToDatabase": "2023-05-01", "Country": {"id": "f635aa2f-6b00-4d7d-b215-33f6256b6350", "label": "Iraq"}, "Date": "2023-05-01", "Grid": {"id": "6ea85f2f-1b06-436a-bfd7-525afbe17263", "label": "E45N31-44"}, "ID": "ddafc4e5-18a9-45cd-b02d-1d114bfaf3a5", "Label": "EAMENA-0078000", "Tiles": [["Resource Summary", 1], ["Geography", 1], ["Geometry", 1], ["Archaeological Assessment ", 1], ["Geometry Location Observation", 1], ["Modern Country Territory", 1], ["Condition State", 1], ["Condition Assessment", 1]]}, {"AddedToDatabase": "2023-05-01", "Country": {"id": "f635aa2f-6b00-4d7d-b215-33f6256b6350", "label": "Iraq"}, "Date": "2023-05-01", "Grid": {"id": "6ea85f2f-1b06-436a-bfd7-525afbe17263", "label": "E45N31-44"}, "ID": "df7e10a6-5505-4491-977b-df388c0719cf", "Label": "EAMENA-0077963", "Tiles": [["Geometry Location Observation", 1], ["Geometry", 1], ["Resource Summary", 1], ["Modern Country Territory", 1], ["Geography", 1], ["Condition State", 1], ["Archaeological Assessment ", 1], ["Condition Assessment", 1]]}, {"AddedToDatabase": "2023-05-01", "Country": {"id": "f635aa2f-6b00-4d7d-b215-33f6256b6350", "label": "Iraq"}, "Date": "2023-05-01", "Grid": {"id": "6ea85f2f-1b06-436a-bfd7-525afbe17263", "label": "E45N31-44"}, "ID": "f14f5e73-95ea-4d1d-a30e-9537f591da2d", "Label": "EAMENA-0077996", "Tiles": [["Condition Assessment", 1], ["Geography", 1], ["Geometry Location Observation", 1], ["Archaeological Assessment ", 1], ["Geometry", 1], ["Resource Summary", 1], ["Condition State", 1], ["Modern Country Territory", 1]]}, {"AddedToDatabase": "2023-05-01", "Country": {"id": "f635aa2f-6b00-4d7d-b215-33f6256b6350", "label": "Iraq"}, "Date": "2023-05-01", "Grid": {"id": "6ea85f2f-1b06-436a-bfd7-525afbe17263", "label": "E45N31-44"}, "ID": "fd4db75a-a24d-4736-9ebb-ce7208da8ca3", "Label": "EAMENA-0077954", "Tiles": [["Geometry", 1], ["Condition State", 1], ["Condition Assessment", 1], ["Resource Summary", 1], ["Geography", 1], ["Archaeological Assessment ", 1], ["Geometry Location Observation", 1], ["Modern Country Territory", 1]]}, {"AddedToDatabase": "2023-05-01", "Country": {"id": "f635aa2f-6b00-4d7d-b215-33f6256b6350", "label": "Iraq"}, "Date": "2023-05-01", "Grid": {"id": "6ea85f2f-1b06-436a-bfd7-525afbe17263", "label": "E45N31-44"}, "ID": "ff20eb06-64c9-4001-94c2-d33b3edf899f", "Label": "EAMENA-0078004", "Tiles": [["Resource Summary", 1], ["Geometry Location Observation", 1], ["Archaeological Assessment ", 1], ["Condition State", 1], ["Condition Assessment", 1], ["Geometry", 1], ["Modern Country Territory", 1], ["Geography", 1]]}, {"AddedToDatabase": "2023-05-01", "Country": {"id": "f635aa2f-6b00-4d7d-b215-33f6256b6350", "label": "Iraq"}, "Date": "2023-05-01", "Grid": {"id": "6ea85f2f-1b06-436a-bfd7-525afbe17263", "label": "E45N31-44"}, "ID": "ff3d95dd-652a-4e69-9f56-d6b9eef7b092", "Label": "EAMENA-0078001", "Tiles": [["Archaeological Assessment ", 1], ["Condition State", 1], ["Resource Summary", 1], ["Geography", 1], ["Condition Assessment", 1], ["Modern Country Territory", 1], ["Geometry Location Observation", 1], ["Geometry", 1]]}]