[{"Actor": {"id": "90ae76cf-865d-4e68-971c-c2b2af9be18c", "label": "Michael Fradley"}, "AddedToDatabase": "2023-05-02", "Country": {"id": "f635aa2f-6b00-4d7d-b215-33f6256b6350", "label": "Iraq"}, "Date": "2022-05-19", "Grid": {"id": "38a7ccc3-a0e2-455c-a11a-e245b0a187c6", "label": "E45N29-31"}, "ID": "049156ea-2ffd-4d6d-86a6-040f36e30b70", "Role": {"id": "20b1a4e0-97e1-41f7-b519-124a7317266b", "label": "EAMENA Project Staff"}, "Label": "EAMENA-0204744", "Tiles": [["Condition State", 1], ["Archaeological Assessment ", 1], ["Modern Country Territory", 1], ["Geometry", 1], ["Environment Assessment", 1], ["Assessment Summary", 1], ["Geography", 1], ["Assessment Activity", 1], ["Resource Summary", 1], ["Condition Assessment", 1], ["Geometry Location Observation", 1]]}, {"Actor": {"id": "90ae76cf-865d-4e68-971c-c2b2af9be18c", "label": "Michael Fradley"}, "AddedToDatabase": "2023-05-02", "Country": {"id": "f635aa2f-6b00-4d7d-b215-33f6256b6350", "label": "Iraq"}, "Date": "2022-05-19", "Grid": {"id": "38a7ccc3-a0e2-455c-a11a-e245b0a187c6", "label": "E45N29-31"}, "ID": "04e3e7b5-4796-4972-9829-5c240e71a67a", "Role": {"id": "20b1a4e0-97e1-41f7-b519-124a7317266b", "label": "EAMENA Project Staff"}, "Label": "EAMENA-0204724", "Tiles": [["Geometry Location Observation", 1], ["Resource Summary", 1], ["Modern Country Territory", 1], ["Archaeological Assessment ", 1], ["Assessment Summary", 1], ["Geography", 1], ["Assessment Activity", 1], ["Geometry", 1], ["Condition Assessment", 1], ["Environment Assessment", 1], ["Condition State", 1]]}, {"Actor": {"id": "90ae76cf-865d-4e68-971c-c2b2af9be18c", "label": "Michael Fradley"}, "AddedToDatabase": "2023-05-02", "Country": {"id": "f635aa2f-6b00-4d7d-b215-33f6256b6350", "label": "Iraq"}, "Date": "2022-05-19", "Grid": {"id": "38a7ccc3-a0e2-455c-a11a-e245b0a187c6", "label": "E45N29-31"}, "ID": "148da519-b369-4e84-a0f9-530fdb1a5cf7", "Role": {"id": "20b1a4e0-97e1-41f7-b519-124a7317266b", "label": "EAMENA Project Staff"}, "Label": "EAMENA-0204723", "Tiles": [["Assessment Summary", 1], ["Modern Country Territory", 1], ["Environment Assessment", 1], ["Geography", 1], ["Assessment Activity", 1], ["Condition Assessment", 1], ["Geometry", 1], ["Archaeological Assessment ", 1], ["Geometry Location Observation", 1], ["Resource Summary", 1], ["Condition State", 1]]}, {"Actor": {"id": "90ae76cf-865d-4e68-971c-c2b2af9be18c", "label": "Michael Fradley"}, "AddedToDatabase": "2023-05-02", "Country": {"id": "f635aa2f-6b00-4d7d-b215-33f6256b6350", "label": "Iraq"}, "Date": "2022-05-19", "Grid": {"id": "38a7ccc3-a0e2-455c-a11a-e245b0a187c6", "label": "E45N29-31"}, "ID": "1d7c034b-c83a-4f6e-9ada-f17d725fbf79", "Role": {"id": "20b1a4e0-97e1-41f7-b519-124a7317266b", "label": "EAMENA Project Staff"}, "Label": "EAMENA-0204721", "Tiles": [["Assessment Activity", 1], ["Assessment Summary", 1], ["Geography", 1], ["Condition Assessment", 1], ["Environment Assessment", 1], ["Condition State", 1], ["Resource Summary", 1], ["Modern Country Territory", 1], ["Archaeological Assessment ", 1], ["Geometry", 1], ["Geometry Location Observation", 1]]}, {"Actor": {"id": "90ae76cf-865d-4e68-971c-c2b2af9be18c", "label": "Michael Fradley"}, "AddedToDatabase": "2023-05-02", "Country": {"id": "f635aa2f-6b00-4d7d-b215-33f6256b6350", "label": "Iraq"}, "Date": "2022-05-19", "Grid": {"id": "38a7ccc3-a0e2-455c-a11a-e245b0a187c6", "label": "E45N29-31"}, "ID": "31cfbbec-988c-4466-8d1d-2076ef43c69c", "Role": {"id": "20b1a4e0-97e1-41f7-b519-124a7317266b", "label": "EAMENA Project Staff"}, "Label": "EAMENA-0204727", "Tiles": [["Assessment Summary", 1], ["Archaeological Assessment ", 1], ["Geometry Location Observation", 1], ["Geometry", 1], ["Geography", 1], ["Condition State", 1], ["Assessment Activity", 1], ["Resource Summary", 1], ["Modern Country Territory", 1], ["Environment Assessment", 1], ["Condition Assessment", 1]]}, {"Actor": {"id": "90ae76cf-865d-4e68-971c-c2b2af9be18c", "label": "Michael Fradley"}, "AddedToDatabase": "2023-05-02", "Country": {"id": "f635aa2f-6b00-4d7d-b215-33f6256b6350", "label": "Iraq"}, "Date": "2022-05-19", "Grid": {"id": "38a7ccc3-a0e2-455c-a11a-e245b0a187c6", "label": "E45N29-31"}, "ID": "52e2bd26-28d4-4c0e-95bf-43cc1cf814cf", "Role": {"id": "20b1a4e0-97e1-41f7-b519-124a7317266b", "label": "EAMENA Project Staff"}, "Label": "EAMENA-0204738", "Tiles": [["Condition State", 1], ["Geometry", 1], ["Assessment Activity", 1], ["Geometry Location Observation", 1], ["Archaeological Assessment ", 1], ["Condition Assessment", 1], ["Modern Country Territory", 1], ["Resource Summary", 1], ["Assessment Summary", 1], ["Geography", 1], ["Environment Assessment", 1]]}, {"Actor": {"id": "90ae76cf-865d-4e68-971c-c2b2af9be18c", "label": "Michael Fradley"}, "AddedToDatabase": "2023-05-02", "Country": {"id": "f635aa2f-6b00-4d7d-b215-33f6256b6350", "label": "Iraq"}, "Date": "2022-05-19", "Grid": {"id": "38a7ccc3-a0e2-455c-a11a-e245b0a187c6", "label": "E45N29-31"}, "ID": "59eb7b0e-e9db-4b1c-bca8-f27b0fd3f376", "Role": {"id": "20b1a4e0-97e1-41f7-b519-124a7317266b", "label": "EAMENA Project Staff"}, "Label": "EAMENA-0204742", "Tiles": [["Geometry", 1], ["Resource Summary", 1], ["Modern Country Territory", 1], ["Condition Assessment", 1], ["Geography", 1], ["Environment Assessment", 1], ["Assessment Summary", 1], ["Assessment Activity", 1], ["Geometry Location Observation", 1], ["Condition State", 1], ["Archaeological Assessment ", 1]]}, {"Actor": {"id": "90ae76cf-865d-4e68-971c-c2b2af9be18c", "label": "Michael Fradley"}, "AddedToDatabase": "2023-05-02", "Country": {"id": "f635aa2f-6b00-4d7d-b215-33f6256b6350", "label": "Iraq"}, "Date": "2022-05-19", "Grid": {"id": "38a7ccc3-a0e2-455c-a11a-e245b0a187c6", "label": "E45N29-31"}, "ID": "75cba7a8-b493-47a5-a992-153daae88efd", "Role": {"id": "20b1a4e0-97e1-41f7-b519-124a7317266b", "label": "EAMENA Project Staff"}, "Label": "EAMENA-0204728", "Tiles": [["Condition State", 1], ["Condition Assessment", 1], ["Geometry", 1], ["Assessment Activity", 1], ["Geometry Location Observation", 1], ["Assessment Summary", 1], ["Geography", 1], ["Modern Country Territory", 1], ["Environment Assessment", 1], ["Archaeological Assessment ", 1], ["Resource Summary", 1]]}, {"Actor": {"id": "90ae76cf-865d-4e68-971c-c2b2af9be18c", "label": "Michael Fradley"}, "AddedToDatabase": "2023-05-02", "Country": {"id": "f635aa2f-6b00-4d7d-b215-33f6256b6350", "label": "Iraq"}, "Date": "2022-05-19", "Grid": {"id": "38a7ccc3-a0e2-455c-a11a-e245b0a187c6", "label": "E45N29-31"}, "ID": "7ccf4bca-babe-4c01-93a9-71f9bb04fba7", "Role": {"id": "20b1a4e0-97e1-41f7-b519-124a7317266b", "label": "EAMENA Project Staff"}, "Label": "EAMENA-0204729", "Tiles": [["Assessment Activity", 1], ["Assessment Summary", 1], ["Archaeological Assessment ", 1], ["Modern Country Territory", 1], ["Geography", 1], ["Condition State", 1], ["Resource Summary", 1], ["Geometry", 1], ["Condition Assessment", 1], ["Environment Assessment", 1], ["Geometry Location Observation", 1]]}, {"Actor": {"id": "90ae76cf-865d-4e68-971c-c2b2af9be18c", "label": "Michael Fradley"}, "AddedToDatabase": "2023-05-02", "Country": {"id": "f635aa2f-6b00-4d7d-b215-33f6256b6350", "label": "Iraq"}, "Date": "2022-05-19", "Grid": {"id": "38a7ccc3-a0e2-455c-a11a-e245b0a187c6", "label": "E45N29-31"}, "ID": "816b9ee2-acda-44ae-9fa5-c12d9fa006a3", "Role": {"id": "20b1a4e0-97e1-41f7-b519-124a7317266b", "label": "EAMENA Project Staff"}, "Label": "EAMENA-0204739", "Tiles": [["Geometry", 1], ["Archaeological Assessment ", 1], ["Condition State", 1], ["Resource Summary", 1], ["Geography", 1], ["Condition Assessment", 1], ["Modern Country Territory", 1], ["Environment Assessment", 1], ["Geometry Location Observation", 1], ["Assessment Activity", 1], ["Assessment Summary", 1]]}, {"Actor": {"id": "90ae76cf-865d-4e68-971c-c2b2af9be18c", "label": "Michael Fradley"}, "AddedToDatabase": "2023-05-02", "Country": {"id": "f635aa2f-6b00-4d7d-b215-33f6256b6350", "label": "Iraq"}, "Date": "2022-05-19", "Grid": {"id": "38a7ccc3-a0e2-455c-a11a-e245b0a187c6", "label": "E45N29-31"}, "ID": "8362ed6a-f84c-4d8b-a516-18fa79bc5eb7", "Role": {"id": "20b1a4e0-97e1-41f7-b519-124a7317266b", "label": "EAMENA Project Staff"}, "Label": "EAMENA-0204725", "Tiles": [["Geometry", 1], ["Assessment Activity", 1], ["Geography", 1], ["Assessment Summary", 1], ["Geometry Location Observation", 1], ["Condition State", 1], ["Condition Assessment", 1], ["Environment Assessment", 1], ["Resource Summary", 1], ["Archaeological Assessment ", 1], ["Modern Country Territory", 1]]}, {"Actor": {"id": "90ae76cf-865d-4e68-971c-c2b2af9be18c", "label": "Michael Fradley"}, "AddedToDatabase": "2023-05-02", "Country": {"id": "f635aa2f-6b00-4d7d-b215-33f6256b6350", "label": "Iraq"}, "Date": "2022-05-19", "Grid": {"id": "38a7ccc3-a0e2-455c-a11a-e245b0a187c6", "label": "E45N29-31"}, "ID": "83bb0350-8f29-4e0a-9df0-7544904a17af", "Role": {"id": "20b1a4e0-97e1-41f7-b519-124a7317266b", "label": "EAMENA Project Staff"}, "Label": "EAMENA-0204743", "Tiles": [["Geometry", 1], ["Condition State", 1], ["Condition Assessment", 1], ["Geography", 1], ["Modern Country Territory", 1], ["Assessment Summary", 1], ["Environment Assessment", 1], ["Archaeological Assessment ", 1], ["Geometry Location Observation", 1], ["Resource Summary", 1], ["Assessment Activity", 1]]}, {"Actor": {"id": "90ae76cf-865d-4e68-971c-c2b2af9be18c", "label": "Michael Fradley"}, "AddedToDatabase": "2023-05-02", "Country": {"id": "f635aa2f-6b00-4d7d-b215-33f6256b6350", "label": "Iraq"}, "Date": "2022-05-19", "Grid": {"id": "38a7ccc3-a0e2-455c-a11a-e245b0a187c6", "label": "E45N29-31"}, "ID": "8576de02-e354-4d82-bada-ec428b27e99a", "Role": {"id": "20b1a4e0-97e1-41f7-b519-124a7317266b", "label": "EAMENA Project Staff"}, "Label": "EAMENA-0204716", "Tiles": [["Geography", 1], ["Modern Country Territory", 1], ["Geometry", 1], ["Condition Assessment", 1], ["Assessment Summary", 1], ["Environment Assessment", 1], ["Archaeological Assessment ", 1], ["Geometry Location Observation", 1], ["Assessment Activity", 1], ["Resource Summary", 1], ["Condition State", 1]]}, {"Actor": {"id": "90ae76cf-865d-4e68-971c-c2b2af9be18c", "label": "Michael Fradley"}, "AddedToDatabase": "2023-05-02", "Country": {"id": "f635aa2f-6b00-4d7d-b215-33f6256b6350", "label": "Iraq"}, "Date": "2022-05-19", "Grid": {"id": "38a7ccc3-a0e2-455c-a11a-e245b0a187c6", "label": "E45N29-31"}, "ID": "87b3bfcc-63b0-4d76-b7fb-a4c8119b52ec", "Role": {"id": "20b1a4e0-97e1-41f7-b519-124a7317266b", "label": "EAMENA Project Staff"}, "Label": "EAMENA-0204732", "Tiles": [["Resource Summary", 1], ["Geometry", 1], ["Archaeological Assessment ", 1], ["Assessment Activity", 1], ["Assessment Summary", 1], ["Condition Assessment", 1], ["Environment Assessment", 1], ["Geography", 1], ["Modern Country Territory", 1], ["Condition State", 1], ["Geometry Location Observation", 1]]}, {"Actor": {"id": "90ae76cf-865d-4e68-971c-c2b2af9be18c", "label": "Michael Fradley"}, "AddedToDatabase": "2023-05-02", "Country": {"id": "f635aa2f-6b00-4d7d-b215-33f6256b6350", "label": "Iraq"}, "Date": "2022-05-19", "Grid": {"id": "38a7ccc3-a0e2-455c-a11a-e245b0a187c6", "label": "E45N29-31"}, "ID": "905f1f2b-fd85-41db-b7e4-c93856050748", "Role": {"id": "20b1a4e0-97e1-41f7-b519-124a7317266b", "label": "EAMENA Project Staff"}, "Label": "EAMENA-0204719", "Tiles": [["Assessment Activity", 1], ["Modern Country Territory", 1], ["Geography", 1], ["Condition State", 1], ["Geometry", 1], ["Environment Assessment", 1], ["Resource Summary", 1], ["Archaeological Assessment ", 1], ["Geometry Location Observation", 1], ["Condition Assessment", 1], ["Assessment Summary", 1]]}, {"Actor": {"id": "90ae76cf-865d-4e68-971c-c2b2af9be18c", "label": "Michael Fradley"}, "AddedToDatabase": "2023-05-02", "Country": {"id": "f635aa2f-6b00-4d7d-b215-33f6256b6350", "label": "Iraq"}, "Date": "2022-05-19", "Grid": {"id": "38a7ccc3-a0e2-455c-a11a-e245b0a187c6", "label": "E45N29-31"}, "ID": "91f47ac7-0d07-4d5c-948b-69b95aa30eea", "Role": {"id": "20b1a4e0-97e1-41f7-b519-124a7317266b", "label": "EAMENA Project Staff"}, "Label": "EAMENA-0204741", "Tiles": [["Resource Summary", 1], ["Geography", 1], ["Assessment Activity", 1], ["Geometry Location Observation", 1], ["Condition State", 1], ["Environment Assessment", 1], ["Modern Country Territory", 1], ["Geometry", 1], ["Archaeological Assessment ", 1], ["Condition Assessment", 1], ["Assessment Summary", 1]]}, {"Actor": {"id": "90ae76cf-865d-4e68-971c-c2b2af9be18c", "label": "Michael Fradley"}, "AddedToDatabase": "2023-05-02", "Country": {"id": "f635aa2f-6b00-4d7d-b215-33f6256b6350", "label": "Iraq"}, "Date": "2022-05-19", "Grid": {"id": "38a7ccc3-a0e2-455c-a11a-e245b0a187c6", "label": "E45N29-31"}, "ID": "95a43a93-e51c-4e34-aa14-a08e3a5e382a", "Role": {"id": "20b1a4e0-97e1-41f7-b519-124a7317266b", "label": "EAMENA Project Staff"}, "Label": "EAMENA-0204726", "Tiles": [["Geometry Location Observation", 1], ["Resource Summary", 1], ["Environment Assessment", 1], ["Geography", 1], ["Condition State", 1], ["Geometry", 1], ["Archaeological Assessment ", 1], ["Assessment Activity", 1], ["Condition Assessment", 1], ["Modern Country Territory", 1], ["Assessment Summary", 1]]}, {"Actor": {"id": "90ae76cf-865d-4e68-971c-c2b2af9be18c", "label": "Michael Fradley"}, "AddedToDatabase": "2023-05-02", "Country": {"id": "f635aa2f-6b00-4d7d-b215-33f6256b6350", "label": "Iraq"}, "Date": "2022-05-19", "Grid": {"id": "38a7ccc3-a0e2-455c-a11a-e245b0a187c6", "label": "E45N29-31"}, "ID": "994a6c48-181c-44a5-ac56-6c2bf717a037", "Role": {"id": "20b1a4e0-97e1-41f7-b519-124a7317266b", "label": "EAMENA Project Staff"}, "Label": "EAMENA-0204740", "Tiles": [["Modern Country Territory", 1], ["Environment Assessment", 1], ["Archaeological Assessment ", 1], ["Condition State", 1], ["Geometry", 1], ["Resource Summary", 1], ["Geometry Location Observation", 1], ["Condition Assessment", 1], ["Assessment Summary", 1], ["Geography", 1], ["Assessment Activity", 1]]}, {"Actor": {"id": "90ae76cf-865d-4e68-971c-c2b2af9be18c", "label": "Michael Fradley"}, "AddedToDatabase": "2023-05-02", "Country": {"id": "f635aa2f-6b00-4d7d-b215-33f6256b6350", "label": "Iraq"}, "Date": "2022-05-19", "Grid": {"id": "38a7ccc3-a0e2-455c-a11a-e245b0a187c6", "label": "E45N29-31"}, "ID": "9d568bb9-8e48-4fd8-b24a-65cc6ec72b71", "Role": {"id": "20b1a4e0-97e1-41f7-b519-124a7317266b", "label": "EAMENA Project Staff"}, "Label": "EAMENA-0204717", "Tiles": [["Resource Summary", 1], ["Assessment Activity", 1], ["Geometry", 1], ["Condition Assessment", 1], ["Geography", 1], ["Archaeological Assessment ", 1], ["Geometry Location Observation", 1], ["Condition State", 1], ["Environment Assessment", 1], ["Modern Country Territory", 1], ["Assessment Summary", 1]]}, {"Actor": {"id": "90ae76cf-865d-4e68-971c-c2b2af9be18c", "label": "Michael Fradley"}, "AddedToDatabase": "2023-05-02", "Country": {"id": "f635aa2f-6b00-4d7d-b215-33f6256b6350", "label": "Iraq"}, "Date": "2022-05-19", "Grid": {"id": "38a7ccc3-a0e2-455c-a11a-e245b0a187c6", "label": "E45N29-31"}, "ID": "b5717d3e-f97d-4c5b-b2a9-2c6a7f278cec", "Role": {"id": "20b1a4e0-97e1-41f7-b519-124a7317266b", "label": "EAMENA Project Staff"}, "Label": "EAMENA-0204734", "Tiles": [["Geography", 1], ["Condition State", 1], ["Modern Country Territory", 1], ["Condition Assessment", 1], ["Assessment Activity", 1], ["Geometry", 1], ["Assessment Summary", 1], ["Resource Summary", 1], ["Environment Assessment", 1], ["Geometry Location Observation", 1], ["Archaeological Assessment ", 1]]}, {"Actor": {"id": "90ae76cf-865d-4e68-971c-c2b2af9be18c", "label": "Michael Fradley"}, "AddedToDatabase": "2023-05-02", "Country": {"id": "f635aa2f-6b00-4d7d-b215-33f6256b6350", "label": "Iraq"}, "Date": "2022-05-19", "Grid": {"id": "38a7ccc3-a0e2-455c-a11a-e245b0a187c6", "label": "E45N29-31"}, "ID": "be326e49-203a-4f07-85b4-4b796b2100f4", "Role": {"id": "20b1a4e0-97e1-41f7-b519-124a7317266b", "label": "EAMENA Project Staff"}, "Label": "EAMENA-0204735", "Tiles": [["Archaeological Assessment ", 1], ["Resource Summary", 1], ["Assessment Summary", 1], ["Condition State", 1], ["Assessment Activity", 1], ["Geography", 1], ["Geometry Location Observation", 1], ["Geometry", 1], ["Condition Assessment", 1], ["Modern Country Territory", 1], ["Environment Assessment", 1]]}, {"Actor": {"id": "90ae76cf-865d-4e68-971c-c2b2af9be18c", "label": "Michael Fradley"}, "AddedToDatabase": "2023-05-03", "Country": {"id": "f635aa2f-6b00-4d7d-b215-33f6256b6350", "label": "Iraq"}, "Date": "2022-05-19", "Grid": {"id": "38a7ccc3-a0e2-455c-a11a-e245b0a187c6", "label": "E45N29-31"}, "ID": "c799bc91-5243-4c6f-900f-266925c82e84", "Role": {"id": "20b1a4e0-97e1-41f7-b519-124a7317266b", "label": "EAMENA Project Staff"}, "Label": "EAMENA-0204720", "Tiles": [["Geography", 1], ["Condition Assessment", 1], ["Assessment Activity", 1], ["Modern Country Territory", 1], ["Geometry Location Observation", 1], ["Environment Assessment", 1], ["Geometry", 1], ["Resource Summary", 1], ["Archaeological Assessment ", 1], ["Condition State", 1], ["Assessment Summary", 1]]}, {"Actor": {"id": "90ae76cf-865d-4e68-971c-c2b2af9be18c", "label": "Michael Fradley"}, "AddedToDatabase": "2023-05-02", "Country": {"id": "f635aa2f-6b00-4d7d-b215-33f6256b6350", "label": "Iraq"}, "Date": "2022-05-19", "Grid": {"id": "38a7ccc3-a0e2-455c-a11a-e245b0a187c6", "label": "E45N29-31"}, "ID": "cbab9f14-b03c-44ae-8c9b-f48081b852b4", "Role": {"id": "20b1a4e0-97e1-41f7-b519-124a7317266b", "label": "EAMENA Project Staff"}, "Label": "EAMENA-0204731", "Tiles": [["Geometry", 1], ["Archaeological Assessment ", 1], ["Environment Assessment", 1], ["Assessment Summary", 1], ["Resource Summary", 1], ["Geometry Location Observation", 1], ["Condition State", 1], ["Modern Country Territory", 1], ["Condition Assessment", 1], ["Geography", 1], ["Assessment Activity", 1]]}, {"Actor": {"id": "90ae76cf-865d-4e68-971c-c2b2af9be18c", "label": "Michael Fradley"}, "AddedToDatabase": "2023-05-02", "Country": {"id": "f635aa2f-6b00-4d7d-b215-33f6256b6350", "label": "Iraq"}, "Date": "2022-05-19", "Grid": {"id": "38a7ccc3-a0e2-455c-a11a-e245b0a187c6", "label": "E45N29-31"}, "ID": "cc32f9fa-7394-46f5-a871-89cff87cef74", "Role": {"id": "20b1a4e0-97e1-41f7-b519-124a7317266b", "label": "EAMENA Project Staff"}, "Label": "EAMENA-0204737", "Tiles": [["Environment Assessment", 1], ["Geography", 1], ["Condition Assessment", 1], ["Assessment Summary", 1], ["Assessment Activity", 1], ["Geometry Location Observation", 1], ["Geometry", 1], ["Modern Country Territory", 1], ["Archaeological Assessment ", 1], ["Resource Summary", 1], ["Condition State", 1]]}, {"Actor": {"id": "90ae76cf-865d-4e68-971c-c2b2af9be18c", "label": "Michael Fradley"}, "AddedToDatabase": "2023-05-02", "Country": {"id": "f635aa2f-6b00-4d7d-b215-33f6256b6350", "label": "Iraq"}, "Date": "2022-05-19", "Grid": {"id": "38a7ccc3-a0e2-455c-a11a-e245b0a187c6", "label": "E45N29-31"}, "ID": "dc971529-77f7-44bb-a30f-843f6c433079", "Role": {"id": "20b1a4e0-97e1-41f7-b519-124a7317266b", "label": "EAMENA Project Staff"}, "Label": "EAMENA-0204722", "Tiles": [["Condition Assessment", 1], ["Geography", 1], ["Resource Summary", 1], ["Geometry Location Observation", 1], ["Assessment Activity", 1], ["Archaeological Assessment ", 1], ["Modern Country Territory", 1], ["Condition State", 1], ["Assessment Summary", 1], ["Environment Assessment", 1], ["Geometry", 1]]}, {"Actor": {"id": "90ae76cf-865d-4e68-971c-c2b2af9be18c", "label": "Michael Fradley"}, "AddedToDatabase": "2023-05-02", "Country": {"id": "f635aa2f-6b00-4d7d-b215-33f6256b6350", "label": "Iraq"}, "Date": "2022-05-19", "Grid": {"id": "38a7ccc3-a0e2-455c-a11a-e245b0a187c6", "label": "E45N29-31"}, "ID": "e3bee3ca-734f-49ff-878f-ece4c46500e7", "Role": {"id": "20b1a4e0-97e1-41f7-b519-124a7317266b", "label": "EAMENA Project Staff"}, "Label": "EAMENA-0204736", "Tiles": [["Geography", 1], ["Modern Country Territory", 1], ["Archaeological Assessment ", 1], ["Assessment Summary", 1], ["Resource Summary", 1], ["Geometry", 1], ["Condition State", 1], ["Condition Assessment", 1], ["Geometry Location Observation", 1], ["Environment Assessment", 1], ["Assessment Activity", 1]]}, {"Actor": {"id": "90ae76cf-865d-4e68-971c-c2b2af9be18c", "label": "Michael Fradley"}, "AddedToDatabase": "2023-05-02", "Country": {"id": "f635aa2f-6b00-4d7d-b215-33f6256b6350", "label": "Iraq"}, "Date": "2022-05-19", "Grid": {"id": "38a7ccc3-a0e2-455c-a11a-e245b0a187c6", "label": "E45N29-31"}, "ID": "f0667eee-ea33-4cb6-aa4a-22e2852c8c58", "Role": {"id": "20b1a4e0-97e1-41f7-b519-124a7317266b", "label": "EAMENA Project Staff"}, "Label": "EAMENA-0204718", "Tiles": [["Geography", 1], ["Environment Assessment", 1], ["Assessment Summary", 1], ["Geometry Location Observation", 1], ["Resource Summary", 1], ["Geometry", 1], ["Condition State", 1], ["Modern Country Territory", 1], ["Assessment Activity", 1], ["Condition Assessment", 1], ["Archaeological Assessment ", 1]]}, {"Actor": {"id": "90ae76cf-865d-4e68-971c-c2b2af9be18c", "label": "Michael Fradley"}, "AddedToDatabase": "2023-05-02", "Country": {"id": "f635aa2f-6b00-4d7d-b215-33f6256b6350", "label": "Iraq"}, "Date": "2022-05-19", "Grid": {"id": "38a7ccc3-a0e2-455c-a11a-e245b0a187c6", "label": "E45N29-31"}, "ID": "f12c2450-9fb6-4fa4-8745-210b2f6941a3", "Role": {"id": "20b1a4e0-97e1-41f7-b519-124a7317266b", "label": "EAMENA Project Staff"}, "Label": "EAMENA-0204730", "Tiles": [["Assessment Summary", 1], ["Archaeological Assessment ", 1], ["Condition State", 1], ["Resource Summary", 1], ["Geometry", 1], ["Modern Country Territory", 1], ["Geometry Location Observation", 1], ["Environment Assessment", 1], ["Geography", 1], ["Condition Assessment", 1], ["Assessment Activity", 1]]}, {"Actor": {"id": "90ae76cf-865d-4e68-971c-c2b2af9be18c", "label": "Michael Fradley"}, "AddedToDatabase": "2023-05-02", "Country": {"id": "f635aa2f-6b00-4d7d-b215-33f6256b6350", "label": "Iraq"}, "Date": "2022-05-19", "Grid": {"id": "38a7ccc3-a0e2-455c-a11a-e245b0a187c6", "label": "E45N29-31"}, "ID": "fb705220-64dd-4b51-a84f-a8fe35941363", "Role": {"id": "20b1a4e0-97e1-41f7-b519-124a7317266b", "label": "EAMENA Project Staff"}, "Label": "EAMENA-0204733", "Tiles": [["Geometry Location Observation", 1], ["Archaeological Assessment ", 1], ["Condition State", 1], ["Geography", 1], ["Condition Assessment", 1], ["Resource Summary", 1], ["Geometry", 1], ["Assessment Activity", 1], ["Assessment Summary", 1], ["Environment Assessment", 1], ["Modern Country Territory", 1]]}]